Workbook

Sheet Contents (Indice)
A1: CONTENTS
B19: Nu Holdings Ltd.
B20: Investors Relations | Relações com Investidores
B21: investors@nubank.com.br
B23: CONSOLIDATED FINANCIAL STATEMENTS IN IFRS | J23: MANAGERIAL INFORMATION
D25: Consolidated Statement of Profit or Loss - Quarter | K25: Non-Performing Loans (NPLs)
D26: Consolidated Statement of Profit or Loss - Accumulated | K26: Operating Figures
D27: Consolidated Statement of Financial Position | K27: Managerial Indicators
D28: Consolidated Statement of Cash Flow | K28: Financing
D29: Revenue Breakdown
D30: Expenses Breakdown
D31: Credit Operations
D32: Write-offs and Recoveries
B36: DEMONSTRAÇÕES FINANCEIRAS CONSOLIDADAS EM IFRS | J36: INFORMAÇÕES GERENCIAIS
D38: Demonstrações do Resultado Consolidadas - Trimestre | K38: Inadimplência
D39: Demonstrações do Resultado Consolidadas - Acumulado | K39: Informações Operacionais
D40: Balanços Patrimoniais Consolidados | K40: Indicadores Gerenciais
D41: Demonstrações Consolidadas do Fluxo de Caixa | K41: Empréstimos
D42: Abertura das Receitas
D43: Abertura das Despesas
D44: Operações de Crédito
D45: Baixas e Recuperação das Carteiras

Sheet Profit or loss (Resultado) - qu
B2: Nu Holdings Ltd. | R2: Nu Holdings Ltd.
B3: Consolidated Statement of Profit or Loss - Quarter | R3: Demonstrações do Resultado Consolidadas - Trimestre
B4: Amounts in thousands of US$, except earnings (loss) per share | R4: Valores em R$ mil, exceto o resultado por ação
B5: Back to Contents | R5: Retornar ao Índice
C9: 3-MONTH PERIOD ENDED | S9: PERÍODO DE 3 MESES FINDOS EM
C10: 31/03/2023 | D10: 44926 | E10: 44834 | F10: 44742 | G10: 44651 | H10: 44561 | I10: 44469 | J10: 44377 | K10: 44286 | L10: 44196 | M10: 44104 | N10: 44012 | O10: 43921 | S10: 31/03/2023 | T10: 44926 | U10: 44834 | V10: 44742 | W10: 44651 | X10: 44561 | Y10: 44469 | Z10: 44377 | AA10: 44286 | AB10: 44196 | AC10: 44104 | AD10: 44012 | AE10: 43921
C11: US$ | D11: US$ | E11: US$ | F11: US$ | G11: US$ | H11: US$ | I11: US$ | J11: US$ | K11: US$ | L11: US$ | M11: US$ | N11: US$ | O11: US$ | S11: R$ | T11: R$ | U11: R$ | V11: R$ | W11: R$ | X11: R$ | Y11: R$ | Z11: R$ | AA11: R$ | AB11: R$ | AC11: R$ | AD11: R$ | AE11: R$
B12: Interest income and gains (losses) on financial instruments | C12: 1255454 | D12: ='Profit or loss (Resultado)-accu'!D12-'Profit or loss (Resultado)-accu'!E12 -> 1095509 | E12: 987248 | F12: 853013 | G12: 619443 | H12: 439550 | I12: 294958 | J12: 184893 | K12: 127345 | L12: 89655 | M12: 70140 | N12: 91884 | O12: 131243 | R12: Receita de juros e ganhos (perdas) sobre instrumentos financeiros | S12: 6518819 | T12: ='Profit or loss (Resultado)-accu'!T12-'Profit or loss (Resultado)-accu'!U12 -> 5733900 | U12: 5155508 | V12: 4237744 | W12: 3236590 | X12: ='Profit or loss (Resultado)-accu'!X12-SUM(Y12:AA12) -> 2397359 | Y12: 1556669 | Z12: 995963 | AA12: 698564 | AB12: ='Profit or loss (Resultado)-accu'!AB12-SUM(AC12:AE12) -> 545202 | AC12: 392276 | AD12: 452564 | AE12: 586984
B13: Fee and commission income | C13: 363213 | D13: ='Profit or loss (Resultado)-accu'!D13-'Profit or loss (Resultado)-accu'!E13 -> 355027 | E13: 319619 | F13: 304548 | G13: 257824 | H13: 196415 | I13: 185949 | J13: 151195 | K13: 117718 | L13: 112910 | M13: 85946 | N13: 70443 | O13: 84912 | R13: Receita de tarifas e comissões | S13: 1885947 | T13: ='Profit or loss (Resultado)-accu'!T13-'Profit or loss (Resultado)-accu'!U13 -> 1860810 | U13: 1674102 | V13: 1507527 | W13: 1347130 | X13: ='Profit or loss (Resultado)-accu'!X13-SUM(Y13:AA13) -> 1076747 | Y13: 977543 | Z13: 814442 | AA13: 645754 | AB13: ='Profit or loss (Resultado)-accu'!AB13-SUM(AC13:AE13) -> 640231 | AC13: 461832 | AD13: 346959 | AE13: 379769
B14: Total revenue | C14: 1618667 | D14: =SUM(D12:D13) -> 1450536 | E14: 1306867 | F14: 1157561 | G14: 877267 | H14: 635965 | I14: 480907 | J14: 336088 | K14: 245063 | L14: 202565 | M14: 156086 | N14: 162327 | O14: 216155 | R14: Total das receitas | S14: 8404766 | T14: ='Profit or loss (Resultado)-accu'!T14-'Profit or loss (Resultado)-accu'!U14 -> 7594710 | U14: 6829610 | V14: 5745271 | W14: 4583720 | X14: ='Profit or loss (Resultado)-accu'!X14-SUM(Y14:AA14) -> 3474106 | Y14: 2534212 | Z14: 1810405 | AA14: 1344318 | AB14: ='Profit or loss (Resultado)-accu'!AB14-SUM(AC14:AE14) -> 1185433 | AC14: 854108 | AD14: 799523 | AE14: 966753
B16: Interest and other financial expenses | C16: -440212 | D16: ='Profit or loss (Resultado)-accu'!D16-'Profit or loss (Resultado)-accu'!E16 -> -407511 | E16: -459889 | F16: -407500 | G16: -273003 | H16: -176972 | I16: -101393 | J16: -57236 | K16: -31743 | L16: -31389 | M16: -23984 | N16: -25321 | O16: -33230 | R16: Juros e outras despesas financeiras | S16: -2285757 | T16: ='Profit or loss (Resultado)-accu'!T16-'Profit or loss (Resultado)-accu'!U16 -> -2139812 | U16: -2401270 | V16: -2027860 | W16: -1426441 | X16: ='Profit or loss (Resultado)-accu'!X16-SUM(Y16:AA16) -> -963772 | Y16: -536084 | Z16: -308313 | AA16: -174129 | AB16: ='Profit or loss (Resultado)-accu'!AB16-SUM(AC16:AE16) -> -183549 | AC16: -131304 | AD16: -124716 | AE16: -148621
B17: Transactional expenses | C17: -52778 | D17: ='Profit or loss (Resultado)-accu'!D17-'Profit or loss (Resultado)-accu'!E17 -> -49468 | E17: -44475 | F17: -48036 | G17: -34448 | H17: -32428 | I17: -28560 | J17: -29782 | K17: -26349 | L17: -39165 | M17: -31910 | N17: -22604 | O17: -33136 | R17: Despesas com transações | S17: -274044 | T17: ='Profit or loss (Resultado)-accu'!T17-'Profit or loss (Resultado)-accu'!U17 -> -259402 | U17: -233199 | V17: -238706 | W17: -179991 | X17: ='Profit or loss (Resultado)-accu'!X17-SUM(Y17:AA17) -> -177687 | Y17: -149355 | Z17: -160427 | AA17: -144540 | AB17: ='Profit or loss (Resultado)-accu'!AB17-SUM(AC17:AE17) -> -224052 | AC17: -171159 | AD17: -111334 | AE17: -148201
B18: Credit loss allowance expenses | C18: -474795 | D18: ='Profit or loss (Resultado)-accu'!D18-'Profit or loss (Resultado)-accu'!E18 -> -415223 | E18: -375474 | F18: -338492 | G18: -275722 | H18: -199676 | I18: -127005 | J18: -82668 | K18: -71294 | L18: -55702 | M18: -32939 | N18: -19019 | O18: -61825 | R18: Despesas com provisão para perdas de crédito | S18: -2465326 | T18: ='Profit or loss (Resultado)-accu'!T18-'Profit or loss (Resultado)-accu'!U18 -> -2175036 | U18: -1963939 | V18: -1677165 | W18: -1440647 | X18: ='Profit or loss (Resultado)-accu'!X18-SUM(Y18:AA18) -> -1088049 | Y18: -669247 | Z18: -445308 | AA18: -391090 | AB18: ='Profit or loss (Resultado)-accu'!AB18-SUM(AC18:AE18) -> -324464 | AC18: -180399 | AD18: -93676 | AE18: -276512
B19: Total cost of financial and transactional services provided | C19: -967785 | D19: =SUM(D16:D18) -> -872202 | E19: -879838 | F19: -794028 | G19: -583173 | H19: -409076 | I19: -256958 | J19: -169686 | K19: -129386 | L19: -126256 | M19: -88833 | N19: -66944 | O19: -128191 | R19: Custo total dos serviços financeiros e transacionais prestados | S19: -5025127 | T19: ='Profit or loss (Resultado)-accu'!T19-'Profit or loss (Resultado)-accu'!U19 -> -4574250 | U19: -4598408 | V19: -3943731 | W19: -3047079 | X19: ='Profit or loss (Resultado)-accu'!X19-SUM(Y19:AA19) -> -2229508 | Y19: -1354686 | Z19: -914048 | AA19: -709759 | AB19: ='Profit or loss (Resultado)-accu'!AB19-SUM(AC19:AE19) -> -732065 | AC19: -482862 | AD19: -329726 | AE19: -573334
B21: Gross profit | C21: 650882 | D21: =SUM(D19,D14) -> 578334 | E21: 427029 | F21: 363533 | G21: 294094 | H21: 226889 | I21: 223949 | J21: 166402 | K21: 115677 | L21: 76309 | M21: 67253 | N21: 95383 | O21: 87964 | R21: Lucro bruto | S21: 3379639 | T21: ='Profit or loss (Resultado)-accu'!T21-'Profit or loss (Resultado)-accu'!U21 -> 3020460 | U21: 2231202 | V21: 1801540 | W21: 1536641 | X21: ='Profit or loss (Resultado)-accu'!X21-SUM(Y21:AA21) -> 1244598 | Y21: 1179526 | Z21: 896357 | AA21: 634559 | AB21: ='Profit or loss (Resultado)-accu'!AB21-SUM(AC21:AE21) -> 453368 | AC21: 371246 | AD21: 469797 | AE21: 393419
B23: Operating expenses | R23: Despesas operacionais
B24: Customer support and operations | C24: -107815 | D24: ='Profit or loss (Resultado)-accu'!D24-'Profit or loss (Resultado)-accu'!E24 -> -105840 | E24: -90249 | F24: -77703 | G24: -61571 | H24: -65762 | I24: -51649 | J24: -40968 | K24: -32130 | L24: -28494 | M24: -28930 | N24: -26427 | O24: -40099 | R24: Suporte e operações ao cliente | S24: -559819 | T24: ='Profit or loss (Resultado)-accu'!T24-'Profit or loss (Resultado)-accu'!U24 -> -553719 | U24: -471563 | V24: -385261 | W24: -321708 | X24: ='Profit or loss (Resultado)-accu'!X24-SUM(Y24:AA24) -> -359504 | Y24: -271606 | Z24: -220682 | AA24: -176252 | AB24: ='Profit or loss (Resultado)-accu'!AB24-SUM(AC24:AE24) -> -172720 | AC24: -157728 | AD24: -130163 | AE24: -179343
B25: General and administrative expenses (G&A) | C25: -236881 | D25: ='Profit or loss (Resultado)-accu'!D25-'Profit or loss (Resultado)-accu'!E25 -> -596876 | E25: =SUM(E26:E27) -> -261778 | F25: =SUM(F26:F27) -> -229505 | G25: =SUM(G26:G27) -> -245108 | H25: =SUM(H26:H27) -> -224231 | I25: =SUM(I26:I27) -> -166527 | J25: =SUM(J26:J27) -> -122295 | K25: =SUM(K26:K27) -> -115848 | L25: =SUM(L26:L27) -> -81633 | ... O25: =SUM(O26:O27) -> -70624 | R25: Despesas gerais e administrativas (G&A) | S25: -1229981 | T25: ='Profit or loss (Resultado)-accu'!T25-'Profit or loss (Resultado)-accu'!U25 -> -3105577 | U25: =SUM(U26:U27) -> -1371964 | V25: =SUM(V26:V27) -> -1128494 | W25: =SUM(W26:W27) -> -1280689 | X25: ='Profit or loss (Resultado)-accu'!X25-SUM(Y25:AA25) -> -1223893 | Y25: =SUM(Y26:Y27) -> -875583 | Z25: =SUM(Z26:Z27) -> -658766 | AA25: =SUM(AA26:AA27) -> -635496 | AB25: ='Profit or loss (Resultado)-accu'!AB25-SUM(AC25:AE25) -> -467838 | AC25: =SUM(AC26:AC27) -> -309134 | AD25: =SUM(AD26:AD27) -> -280644 | AE25: =SUM(AE26:AE27) -> -315866
B26: G&A - Contingent share award (CSA) termination | C26: - | D26: ='Profit or loss (Resultado)-accu'!D26-'Profit or loss (Resultado)-accu'!E26 -> -355573 | E26: 0 | F26: 0 | G26: 0 | H26: 0 | I26: 0 | J26: 0 | K26: 0 | L26: 0 | M26: 0 | N26: 0 | O26: 0 | R26: G&A - Rescisão do plano de opções de ações contingentes (CSA) | S26: - | T26: ='Profit or loss (Resultado)-accu'!T26-'Profit or loss (Resultado)-accu'!U26 -> -1836641 | U26: 0 | V26: 0 | W26: 0 | X26: ='Profit or loss (Resultado)-accu'!X26-SUM(Y26:AA26) -> 0 | Y26: 0 | Z26: 0 | AA26: 0 | AB26: ='Profit or loss (Resultado)-accu'!AB26-SUM(AC26:AE26) -> 0 | AC26: 0 | AD26: 0 | AE26: 0
B27: G&A - Other | C27: -236881 | D27: ='Profit or loss (Resultado)-accu'!D27-'Profit or loss (Resultado)-accu'!E27 -> -241303 | E27: -261778 | F27: -229505 | G27: -245108 | H27: -224231 | I27: -166527 | J27: -122295 | K27: -115848 | L27: -81633 | M27: -56788 | N27: -56979 | O27: -70624 | R27: G&A - Outras | S27: -1229981 | T27: ='Profit or loss (Resultado)-accu'!T27-'Profit or loss (Resultado)-accu'!U27 -> -1268936 | U27: -1371964 | V27: -1128494 | W27: -1280689 | X27: ='Profit or loss (Resultado)-accu'!X27-SUM(Y27:AA27) -> -1223893 | Y27: -875583 | Z27: -658766 | AA27: -635496 | AB27: ='Profit or loss (Resultado)-accu'!AB27-SUM(AC27:AE27) -> -467838 | AC27: -309134 | AD27: -280644 | AE27: -315866
B28: Marketing expenses | C28: -19272 | D28: ='Profit or loss (Resultado)-accu'!D28-'Profit or loss (Resultado)-accu'!E28 -> -51078 | E28: -38103 | F28: -36208 | G28: -27608 | H28: -34508 | I28: -25568 | J28: -14631 | K28: -4867 | L28: -7900 | M28: -4088 | N28: -1345 | O28: -6093 | R28: Despesa de marketing | S28: -100068 | T28: ='Profit or loss (Resultado)-accu'!T28-'Profit or loss (Resultado)-accu'!U28 -> -266952 | U28: -199387 | V28: -179684 | W28: -144252 | X28: ='Profit or loss (Resultado)-accu'!X28-SUM(Y28:AA28) -> -188555 | Y28: -135339 | Z28: -78813 | AA28: -26698 | AB28: ='Profit or loss (Resultado)-accu'!AB28-SUM(AC28:AE28) -> -44445 | AC28: -21975 | AD28: -6625 | AE28: -27251
B29: Other income (expenses) | C29: -43285 | D29: ='Profit or loss (Resultado)-accu'!D29-'Profit or loss (Resultado)-accu'!E29 -> -46285 | E29: -31792 | F29: -44729 | G29: -27458 | H29: 9110 | I29: -1962 | J29: 4954 | K29: -16199 | L29: 15911 | M29: -2106 | N29: -5692 | O29: -17648 | R29: Outras receitas (despesas) | S29: -224753 | T29: ='Profit or loss (Resultado)-accu'!T29-'Profit or loss (Resultado)-accu'!U29 -> -242258 | U29: -167473 | V29: -222960 | W29: -143468 | X29: ='Profit or loss (Resultado)-accu'!X29-SUM(Y29:AA29) -> 49935 | Y29: -9869 | Z29: 26686 | AA29: -88861 | AB29: ='Profit or loss (Resultado)-accu'!AB29-SUM(AC29:AE29) -> 72172 | AC29: -14435 | AD29: -28035 | AE29: -78931
B30: Total operating expenses | C30: -407253 | D30: =SUM(D24:D25,D28:D29) -> -800079 | E30: -421922 | F30: -388145 | G30: -361745 | H30: -315391 | I30: -245706 | J30: -172940 | K30: -169044 | L30: -102116 | M30: -91912 | N30: -90443 | O30: -134464 | R30: Total das despesas operacionais | S30: -2114621 | T30: ='Profit or loss (Resultado)-accu'!T30-'Profit or loss (Resultado)-accu'!U30 -> -4168506 | U30: -2210387 | V30: -1916399 | W30: -1890117 | X30: ='Profit or loss (Resultado)-accu'!X30-SUM(Y30:AA30) -> -1722017 | Y30: -1292397 | Z30: -931575 | AA30: -927307 | AB30: ='Profit or loss (Resultado)-accu'!AB30-SUM(AC30:AE30) -> -612831 | AC30: -503272 | AD30: -445467 | AE30: -601391
B32: Results with convertible instruments | C32: - | D32: 0 | E32: 0 | F32: 0 | G32: 0 | H32: 0 | I32: 0 | J32: 0 | K32: 0 | L32: -87965 | M32: -13187 | N32: 0 | O32: 0 | R32: Custos financeiros - resultados com instrumentos conversíveis | S32: - | U32: 0 | V32: 0 | W32: 0 | X32: ='Profit or loss (Resultado)-accu'!X32-SUM(Y32:AA32) -> 0 | Y32: 0 | Z32: 0 | AA32: 0 | AB32: ='Profit or loss (Resultado)-accu'!AB32-SUM(AC32:AE32) -> -455191 | AC32: -67056 | AD32: 0 | AE32: 0
B34: Profit or loss before income taxes | C34: 243629 | D34: =SUM(D30,D21) -> -221745 | E34: 5107 | F34: -24612 | G34: -67651 | H34: -88502 | I34: -21757 | J34: -6538 | K34: -53367 | L34: -113772 | M34: -37846 | N34: 4940 | O34: -46500 | R34: Resultado antes dos tributos | S34: 1265018 | T34: ='Profit or loss (Resultado)-accu'!T34-'Profit or loss (Resultado)-accu'!U34 -> -1148046 | U34: 20815 | V34: -114859 | W34: -353476 | X34: ='Profit or loss (Resultado)-accu'!X34-SUM(Y34:AA34) -> -477419 | Y34: -112871 | Z34: -35218 | AA34: -292748 | AB34: ='Profit or loss (Resultado)-accu'!AB34-SUM(AC34:AE34) -> -614654 | AC34: -199082 | AD34: 24330 | AE34: -207972
B36: Income taxes | R36: Resultado com tributos
B37: Current taxes | C37: -205864 | D37: ='Profit or loss (Resultado)-accu'!D37-'Profit or loss (Resultado)-accu'!E37 -> -171225 | E37: -106819 | F37: -96249 | G37: -99052 | H37: -69694 | I37: -66374 | J37: -52248 | K37: -31508 | L37: -13231 | M37: -182 | N37: -2588 | O37: -6337 | R37: Tributos correntes | S37: -1068928 | T37: ='Profit or loss (Resultado)-accu'!T37-'Profit or loss (Resultado)-accu'!U37 -> -893673 | U37: -559929 | V37: -473820 | W37: -517547 | X37: ='Profit or loss (Resultado)-accu'!X37-SUM(Y37:AA37) -> -382372 | Y37: -349580 | Z37: -281444 | AA37: -172840 | AB37: ='Profit or loss (Resultado)-accu'!AB37-SUM(AC37:AE37) -> -71892 | AC37: -2350 | AD37: -12747 | AE37: -28342
B38: Deferred taxes | C38: 103986 | D38: ='Profit or loss (Resultado)-accu'!D38-'Profit or loss (Resultado)-accu'!E38 -> 95357 | E38: 109545 | F38: 91011 | G38: 121699 | H38: 91922 | I38: 53774 | J38: 43566 | K38: 35392 | L38: 19946 | M38: 5466 | N38: -791 | O38: 19404 | R38: Tributos diferidos | S38: 539937 | T38: ='Profit or loss (Resultado)-accu'!T38-'Profit or loss (Resultado)-accu'!U38 -> 502408 | U38: 574946 | V38: 443860 | W38: 635877 | X38: ='Profit or loss (Resultado)-accu'!X38-SUM(Y38:AA38) -> 500847 | Y38: 282630 | Z38: 234677 | AA38: 194146 | AB38: ='Profit or loss (Resultado)-accu'!AB38-SUM(AC38:AE38) -> 113647 | AC38: 30766 | AD38: -3896 | AE38: 86784
B39: Total income taxes | C39: -101878 | D39: =SUM(D37:D38) -> -75868 | E39: 2726 | F39: -5238 | G39: 22647 | H39: 22228 | I39: -12600 | J39: -8682 | K39: 3884 | L39: 6715 | M39: 5284 | N39: -3379 | O39: 13067 | R39: Total do resultado com tributos | S39: -528991 | T39: ='Profit or loss (Resultado)-accu'!T39-'Profit or loss (Resultado)-accu'!U39 -> -391265 | U39: 15017 | V39: -29960 | W39: 118330 | X39: ='Profit or loss (Resultado)-accu'!X39-SUM(Y39:AA39) -> 118475 | Y39: -66950 | Z39: -46767 | AA39: 21306 | AB39: ='Profit or loss (Resultado)-accu'!AB39-SUM(AC39:AE39) -> 41755 | AC39: 28416 | AD39: -16643 | AE39: 58442
B41: Profit (Loss) for the period/year | C41: 141751 | D41: =SUM(D39,D34) -> -297613 | E41: 7833 | F41: -29850 | G41: -45004 | H41: -66274 | I41: -34357 | J41: -15220 | K41: -49483 | L41: -107057 | M41: -32562 | N41: 1561 | O41: -33433 | R41: Resultado para o período | S41: 736027 | T41: ='Profit or loss (Resultado)-accu'!T41-'Profit or loss (Resultado)-accu'!U41 -> -1539311 | U41: 35832 | V41: -144819 | W41: -235146 | X41: ='Profit or loss (Resultado)-accu'!X41-SUM(Y41:AA41) -> -358944 | Y41: -179821 | Z41: -81985 | AA41: -271442 | AB41: ='Profit or loss (Resultado)-accu'!AB41-SUM(AC41:AE41) -> -572899 | AC41: -170666 | AD41: 7687 | AE41: -149530
B42: Profit (Loss) attributable to shareholders of the parent company | C42: 141751 | D42: ='Profit or loss (Resultado)-accu'!D42-'Profit or loss (Resultado)-accu'!E42 -> -297613 | E42: 7833 | F42: -29697 | G42: -45101 | H42: -66078 | I42: -34212 | J42: -15220 | K42: -49483 | L42: -107057 | M42: -32562 | N42: 1561 | O42: -33433 | R42: Resultado atribuído aos controladores | S42: 736027 | T42: ='Profit or loss (Resultado)-accu'!T42-'Profit or loss (Resultado)-accu'!U42 -> -1539311 | U42: 35832 | V42: -144028 | W42: -235653 | X42: ='Profit or loss (Resultado)-accu'!X42-SUM(Y42:AA42) -> -357877 | Y42: -179048 | Z42: -81985 | AA42: -271442 | AB42: ='Profit or loss (Resultado)-accu'!AB42-SUM(AC42:AE42) -> -572899 | AC42: -170666 | AD42: 7687 | AE42: -149530
B43: Profit (Loss) attributable to non-controlling interests | C43: - | D43: ='Profit or loss (Resultado)-accu'!D43-'Profit or loss (Resultado)-accu'!E43 -> 0 | E43: 0 | F43: -153 | G43: 97 | H43: -196 | I43: -145 | J43: 0 | K43: 0 | L43: 0 | M43: 0 | N43: 0 | O43: 0 | R43: Resultado atribuído aos não controladores (minoritários) | S43: - | T43: ='Profit or loss (Resultado)-accu'!T43-'Profit or loss (Resultado)-accu'!U43 -> 0 | U43: 0 | V43: -791 | W43: 507 | X43: ='Profit or loss (Resultado)-accu'!X43-SUM(Y43:AA43) -> -1067 | Y43: -773 | Z43: 0 | AA43: 0 | AB43: 0 | AD43: 0 | AE43: 0
B45: Earnings (Loss) per share – Basic | C45: 0.0301 | D45: ='Profit or loss (Resultado)-accu'!D45-'Profit or loss (Resultado)-accu'!E45 -> -0.063654018 | E45: 0.0016723476 | F45: -0.0063905328 | G45: -0.0096774851 | H45: -0.0313 | I45: -0.024 | J45: -0.01114 | K45: -0.0367 | L45: -0.0812 | M45: -0.0247 | N45: 0.00119 | O45: -0.0258 | R45: Resultado por ação - básico | S45: 0.1563 | T45: ='Profit or loss (Resultado)-accu'!T45-'Profit or loss (Resultado)-accu'!U45 -> -0.3102 | U45: 0.0077 | V45: -0.030834696 | W45: -0.050564919 | X45: -0.1732 | Y45: -0.1257 | Z45: -0.05999 | AA45: -0.2015 | AB45: -0.4229 | AC45: -0.1292 | AD45: 0.00586 | AE45: -0.1153
B47: Earnings (Loss) per share – Diluted | C47: 0.0294 | D47: ='Profit or loss (Resultado)-accu'!D47-'Profit or loss (Resultado)-accu'!E47 -> -0.063654018 | E47: 0.0016237458 | F47: -0.0063905328 | G47: -0.0096774851 | H47: -0.0313 | I47: -0.024 | J47: -0.01114 | K47: -0.0367 | L47: -0.0812 | M47: -0.0247 | N47: 0.00037 | O47: -0.0258 | R47: Resultado por ação - diluído | S47: 0.1532 | T47: ='Profit or loss (Resultado)-accu'!T47-'Profit or loss (Resultado)-accu'!U47 -> -0.3102 | U47: 0.0074 | V47: -0.030834696 | W47: -0.050564919 | X47: -0.1732 | Y47: -0.1257 | Z47: -0.05999 | AA47: -0.2015 | AB47: -0.4229 | AC47: -0.1292 | AD47: 0.00184 | AE47: -0.1153
B49: Weighted average number of outstanding shares – Basic (in thousands of shares) | C49: 4709505 | D49: 4676977 | E49: 4683835 | F49: 4670972 | G49: 4660405 | H49: 1602126 | I49: 1423876 | J49: 1366612 | K49: 1347258 | L49: 1315578 | M49: 1320606 | N49: 1312236 | O49: 1296708 | R49: Número médio ponderado de ações em circulação - básica (em milhares de ações) | S49: 4709505 | T49: 4676977 | U49: 4683835 | V49: 4670972 | W49: 4660405 | X49: 1602126 | Y49: 1423876 | Z49: 1366612 | AA49: 1347258 | AB49: 1315578 | AC49: 1320606 | AD49: 1312236 | AE49: 1296708
B51: Weighted average number of outstanding shares – Diluted (in thousands of shares) | C51: 4818200 | D51: 4676977 | E51: 4824031 | F51: 4670972 | G51: 4660405 | H51: 1602126 | I51: 1423876 | J51: 1366612 | K51: 1347258 | L51: 1315578 | M51: 1320606 | N51: 4170423 | O51: 1296708 | R51: Número médio ponderado de ações em circulação - diluída (em milhares de ações) | S51: 4818200 | T51: 4676977 | U51: 4824031 | V51: 4670972 | W51: 4660405 | X51: 1602126 | Y51: 1423876 | Z51: 1366612 | AA51: 1347258 | AB51: 1315578 | AC51: 1320606 | AD51: 4170423 | AE51: 1296708

Sheet Profit or loss (Resultado)-accu
B2: Nu Holdings Ltd. | R2: Nu Holdings Ltd.
B3: Consolidated Statement of Profit or Loss - Accumulated | R3: Demonstrações do Resultado Consolidadas - Acumulado
B4: Amounts in thousands of US$, except earnings (loss) per share | R4: Valores em R$ mil, exceto o resultado por ação
B5: Back to Contents | R5: Retornar ao Índice
C9: ACCUMULATED | S9: ACUMULADO
C10: 31/03/2023 | D10: 31/12/2022 | E10: 44834 | F10: 44742 | G10: 44651 | H10: 44561 | I10: 44469 | J10: 44377 | K10: 44286 | L10: 44196 | M10: 44104 | N10: 44012 | O10: 43921 | S10: 31/03/2023 | T10: 44926 | U10: 44834 | V10: 44742 | W10: 44651 | X10: 44561 | Y10: 44469 | Z10: 44377 | AA10: 44286 | AB10: 44196 | AC10: 44104 | AD10: 44012 | AE10: 43921
C11: US$ | D11: US$ | E11: US$ | F11: US$ | G11: US$ | H11: US$ | I11: US$ | J11: US$ | K11: US$ | L11: US$ | M11: US$ | N11: US$ | O11: US$ | S11: R$ | T11: R$ | U11: R$ | V11: R$ | W11: R$ | X11: R$ | Y11: R$ | Z11: R$ | AA11: R$ | AB11: R$ | AC11: R$ | AD11: R$ | AE11: R$
B12: Interest income and gains (losses) on financial instruments | C12: 1255454 | D12: 3555213 | E12: 2459704 | F12: 1472456 | G12: 619443 | H12: 1046746 | I12: 607196 | J12: 312238 | K12: 127345 | L12: 382922 | M12: 293267 | N12: 223127 | O12: 131243 | R12: Receita de juros e ganhos (perdas) sobre instrumentos financeiros | S12: 6518819 | T12: 18363742 | U12: 12629842 | V12: 7474334 | W12: 3236590 | X12: 5648555 | Y12: 3238601 | Z12: 1681932 | AA12: 698564 | AB12: 1977026 | AC12: 1491263 | AD12: 1098987 | AE12: 586984
B13: Fee and commission income | C13: 363213 | D13: 1237018 | E13: 881991 | F13: 562372 | G13: 257824 | H13: 651277 | I13: 454862 | J13: 268913 | K13: 117718 | L13: 354211 | M13: 241301 | N13: 155355 | O13: 84912 | R13: Receita de tarifas e comissões | S13: 1885947 | T13: 6389569 | U13: 4528759 | V13: 2854657 | W13: 1347130 | X13: 3514486 | Y13: 2426097 | Z13: 1448554 | AA13: 645754 | AB13: 1828791 | AC13: 1227016 | AD13: 765184 | AE13: 379769
B14: Total revenue | C14: 1618667 | D14: =SUM(D12:D13) -> 4792231 | E14: 3341695 | F14: 2034828 | G14: 877267 | H14: =SUM(H12:H13) -> 1698023 | I14: 1062058 | J14: 581151 | K14: 245063 | L14: 737133 | M14: 534568 | N14: 378482 | O14: 216155 | R14: Total das receitas | S14: 8404766 | T14: 24753311 | U14: 17158601 | V14: 10328991 | W14: 4583720 | X14: 9163041 | Y14: 5664698 | Z14: 3130486 | AA14: 1344318 | AB14: 3805817 | AC14: 2718279 | AD14: 1864171 | AE14: 966753
B16: Interest and other financial expenses | C16: -440212 | D16: -1547903 | E16: -1140392 | F16: -680503 | G16: -273003 | H16: -367344 | I16: -190372 | J16: -88979 | K16: -31743 | L16: -113924 | M16: -82535 | N16: -58551 | O16: -33230 | R16: Juros e outras despesas financeiras | S16: -2285757 | T16: -7995383 | U16: -5855571 | V16: -3454301 | W16: -1426441 | X16: -1982298 | Y16: -1015387 | Z16: -479303 | AA16: -174129 | AB16: -588190 | AC16: -419690 | AD16: -288386 | AE16: -148621
B17: Transactional expenses | C17: -52778 | D17: -176427 | E17: -126959 | F17: -82484 | G17: -34448 | H17: -117119 | I17: -84691 | J17: -56131 | K17: -26349 | L17: -126815 | M17: -87650 | N17: -55740 | O17: -33136 | R17: Despesas com transações | S17: -274044 | T17: -911298 | U17: -651896 | V17: -418697 | W17: -179991 | X17: -632009 | Y17: -451716 | Z17: -302361 | AA17: -144540 | AB17: -654746 | AC17: -445700 | AD17: -274541 | AE17: -148201
B18: Credit loss allowance expenses | C18: -474795 | D18: -1404911 | E18: -989688 | F18: -614214 | G18: -275722 | H18: -480643 | I18: -280967 | J18: -153962 | K18: -71294 | L18: -169485 | M18: -113783 | N18: -80844 | O18: -61825 | R18: Despesas com provisão para perdas de crédito | S18: -2465326 | T18: -7256787 | U18: -5081751 | V18: -3117812 | W18: -1440647 | X18: -2593694 | Y18: -1498594 | Z18: -829347 | AA18: -391090 | AB18: -875051 | AC18: -578587 | AD18: -398188 | AE18: -276512
B19: Total cost of financial and transactional services provided | C19: -967785 | D19: =SUM(D16:D18) -> -3129241 | E19: -2257039 | F19: -1377201 | G19: -583173 | H19: -965106 | I19: -556030 | J19: -299072 | K19: -129386 | L19: -410224 | M19: -283968 | N19: -195135 | O19: -128191 | R19: Custo total dos serviços financeiros e transacionais prestados | S19: -5025127 | T19: -16163468 | U19: -11589218 | V19: -6990810 | W19: -3047079 | X19: -5208001 | Y19: -2965697 | Z19: -1611011 | AA19: -709759 | AB19: -2117987 | AC19: -1443977 | AD19: -961115 | AE19: -573334
B21: Gross profit | C21: 650882 | D21: =SUM(D14,D19) -> 1662990 | E21: 1084656 | F21: 657627 | G21: 294094 | H21: 732917 | I21: 506028 | J21: 282079 | K21: 115677 | L21: 326909 | M21: 250600 | N21: 183347 | O21: 87964 | R21: Lucro bruto | S21: 3379639 | T21: 8589843 | U21: 5569383 | V21: 3338181 | W21: 1536641 | X21: 3955040 | Y21: 2699001 | Z21: 1519475 | AA21: 634559 | AB21: 1687830 | AC21: 1274302 | AD21: 903056 | AE21: 393419
B23: Operating expenses | R23: Despesas operacionais
B24: Customer support and operations | C24: -107815 | D24: -335363 | E24: -229523 | F24: -139274 | G24: -61571 | H24: -190509 | I24: -124747 | J24: -73098 | K24: -32130 | L24: -123950 | M24: -95456 | N24: -66526 | O24: -40099 | R24: Suporte e operações ao cliente | S24: -559819 | T24: -1732251 | U24: -1178532 | V24: -706969 | W24: -321708 | X24: -1028044 | Y24: -665363 | Z24: -393757 | AA24: -176252 | AB24: -639954 | AC24: -485394 | AD24: -327666 | AE24: -179343
B25: General and administrative expenses (G&A) | C25: -236881 | D25: =SUM(D26:D27) -> -1333267 | E25: =SUM(E26:E27) -> -736391 | F25: =SUM(F26:F27) -> -474613 | G25: =SUM(G26:G27) -> -245108 | H25: =SUM(H26:H27) -> -628901 | I25: =SUM(I26:I27) -> -404670 | J25: =SUM(J26:J27) -> -238143 | K25: =SUM(K26:K27) -> -115848 | ... O25: =SUM(O26:O27) -> -70624 | R25: Despesas gerais e administrativas (G&A) | S25: -1229981 | T25: =SUM(T26:T27) -> -6886724 | U25: =SUM(U26:U27) -> -3781147 | V25: =SUM(V26:V27) -> -2409183 | W25: =SUM(W26:W27) -> -1280689 | X25: =SUM(X26:X27) -> -3393738 | Y25: =SUM(Y26:Y27) -> -2158388 | Z25: =SUM(Z26:Z27) -> -1282805 | AA25: =SUM(AA26:AA27) -> -635496 | ... AE25: =SUM(AE26:AE27) -> -315866
B26: G&A - Contingent share award (CSA) termination | C26: - | D26: -355573 | E26: 0 | F26: 0 | G26: 0 | H26: 0 | I26: 0 | J26: 0 | K26: 0 | L26: 0 | M26: 0 | N26: 0 | O26: 0 | R26: G&A - Rescisão do plano de opções de ações contingentes (CSA) | S26: - | T26: -1836641 | U26: 0 | V26: 0 | W26: 0 | X26: 0 | Y26: 0 | Z26: 0 | AA26: 0 | AB26: 0 | AC26: 0 | AD26: 0 | AE26: 0
B27: G&A - Other | C27: -236881 | D27: -977694 | E27: -736391 | F27: -474613 | G27: -245108 | H27: -628901 | I27: -404670 | J27: -238143 | K27: -115848 | L27: -266024 | M27: -184391 | N27: -127603 | O27: -70624 | R27: G&A - Outras | S27: -1229981 | T27: -5050083 | U27: -3781147 | V27: -2409183 | W27: -1280689 | X27: -3393738 | Y27: -2158388 | Z27: -1282805 | AA27: -635496 | AB27: -1373482 | AC27: -937628 | AD27: -628494 | AE27: -315866
B28: Marketing expenses | C28: -19272 | D28: -152997 | E28: -101919 | F28: -63816 | G28: -27608 | H28: -79574 | I28: -45066 | J28: -19498 | K28: -4867 | L28: -19426 | M28: -11526 | N28: -7438 | O28: -6093 | R28: Despesa de marketing | S28: -100068 | T28: -790275 | U28: -523323 | V28: -323936 | W28: -144252 | X28: -429405 | Y28: -240369 | Z28: -105030 | AA28: -26698 | AB28: -100296 | AC28: -58610 | AD28: -36635 | AE28: -27251
B29: Other income (expenses) | C29: -43285 | D29: -150264 | E29: -103979 | F29: -72187 | G29: -27458 | H29: -4097 | I29: -13207 | J29: -11245 | K29: -16199 | L29: -9535 | M29: -25446 | N29: -23340 | O29: -17648 | R29: Outras receitas (despesas) | S29: -224753 | T29: -776159 | U29: -533901 | V29: -366428 | W29: -143468 | X29: -22109 | Y29: -70442 | Z29: -60573 | AA29: -88861 | AB29: -49229 | AC29: -129394 | AD29: -114959 | AE29: -78931
B30: Total operating expenses | C30: -407253 | D30: =SUM(D24:D25,D28:D29) -> -1971891 | E30: =SUM(E24:E25,E28:E29) -> -1171812 | F30: =SUM(F24:F25,F28:F29) -> -749890 | G30: =SUM(G24:G25,G28:G29) -> -361745 | H30: =SUM(H24:H25,H28:H29) -> -903081 | I30: =SUM(I24:I25,I28:I29) -> -587690 | J30: =SUM(J24:J25,J28:J29) -> -341984 | K30: =SUM(K24:K25,K28:K29) -> -169044 | ... O30: =SUM(O24:O25,O28:O29) -> -134464 | R30: Total das despesas operacionais | S30: -2114621 | T30: -10185409 | U30: -6016903 | V30: -3806516 | W30: -1890117 | X30: -4873296 | Y30: -3134562 | Z30: -1842165 | AA30: -927307 | AB30: -2162961 | AC30: -1611026 | AD30: -1107754 | AE30: -601391
B32: Results with convertible instruments | C32: - | D32: 0 | E32: 0 | F32: 0 | G32: 0 | H32: 0 | I32: 0 | J32: 0 | K32: 0 | L32: -101152 | M32: -13187 | N32: 0 | O32: 0 | R32: Custos financeiros - resultados com instrumentos conversíveis | S32: - | T32: 0 | U32: 0 | V32: 0 | W32: 0 | X32: 0 | Y32: 0 | Z32: 0 | AA32: 0 | AB32: -522247 | AC32: -67056 | AD32: 0 | AE32: 0
B34: Profit (loss) before income taxes | C34: 243629 | D34: =SUM(D21,D30) -> -308901 | E34: -87156 | F34: -92263 | G34: -67651 | H34: -170164 | I34: -81662 | J34: -59905 | K34: -53367 | L34: -193178 | M34: -79406 | N34: -41560 | O34: -46500 | R34: Resultado antes dos tributos sobre o lucro | S34: 1265018 | T34: -1595566 | U34: -447520 | V34: -468335 | W34: -353476 | X34: -918256 | Y34: -435561 | Z34: -322690 | AA34: -292748 | AB34: -997378 | AC34: -403780 | AD34: -204698 | AE34: -207972
B36: Income taxes | R36: Tributos sobre o lucro
B37: Current taxes | C37: -205864 | D37: -473345 | E37: -302120 | F37: -195301 | G37: -99052 | H37: -219824 | I37: -150130 | J37: -83756 | K37: -31508 | L37: -22338 | M37: -9107 | N37: -8925 | O37: -6337 | R37: Tributos correntes | S37: -1068928 | T37: -2444969 | U37: -1551296 | V37: -991367 | W37: -517547 | X37: -1186236 | Y37: -800748 | Z37: -451168 | AA37: -172840 | AB37: -115331 | AC37: -46309 | AD37: -43959 | AE37: -28342
B38: Deferred taxes | C38: 103986 | D38: 417612 | E38: 322255 | F38: 212710 | G38: 121699 | H38: 224654 | I38: 132732 | J38: 78958 | K38: 35392 | L38: 44025 | M38: 24079 | N38: 18613 | O38: 19404 | R38: Tributos diferidos | S38: 539937 | T38: 2157091 | U38: 1654683 | V38: 1079737 | W38: 635877 | X38: 1212300 | Y38: 707953 | Z38: 425323 | AA38: 194146 | AB38: 227301 | AC38: 122442 | AD38: 91676 | AE38: 86784
B39: Total income taxes | C39: -101878 | D39: =SUM(D37:D38) -> -55733 | E39: 20135 | F39: 17409 | G39: 22647 | H39: 4830 | I39: -17398 | J39: -4798 | K39: 3884 | L39: 21687 | M39: 14972 | N39: 9688 | O39: 13067 | R39: Total dos tributos sobre o lucro | S39: -528991 | T39: -287878 | U39: 103387 | V39: 88370 | W39: 118330 | X39: 26064 | Y39: -92795 | Z39: -25845 | AA39: 21306 | AB39: 111970 | AC39: 76133 | AD39: 47717 | AE39: 58442
B41: Profit (Loss) for the period/year | C41: 141751 | D41: =SUM(D34,D39) -> -364634 | E41: -67021 | F41: -74854 | G41: -45004 | H41: -165334 | I41: -99060 | J41: -64703 | K41: -49483 | L41: -171491 | M41: -64434 | N41: -31872 | O41: -33433 | R41: Lucro (Prejuízo) do período / exercício | S41: 736027 | T41: -1883444 | U41: -344133 | V41: -379965 | W41: -235146 | X41: -892192 | Y41: -528356 | Z41: -348535 | AA41: -271442 | AB41: -885408 | AC41: -327647 | AD41: -156981 | AE41: -149530
B42: Profit (Loss) attributable to shareholders of the parent company | C42: 141751 | D42: -364578 | E42: -66965 | F42: -74798 | G42: -45101 | H42: -164993 | I42: -98915 | J42: -64703 | K42: -49483 | L42: -171491 | M42: -64434 | N42: -31872 | O42: -33433 | R42: Lucro (Prejuízo) atribuído aos controladores | S42: 736027 | T42: -1883160 | U42: -343849 | V42: -379681 | W42: -235653 | X42: -890352 | Y42: -527583 | Z42: -348535 | AA42: -271442 | AB42: -885408 | AC42: -327647 | AD42: -156981 | AE42: -149530
B43: Profit (Loss) attributable to non-controlling interests | C43: - | D43: -56 | E43: -56 | F43: -56 | G43: 97 | H43: -341 | I43: -145 | J43: 0 | K43: 0 | L43: 0 | M43: 0 | N43: - | O43: 0 | R43: Lucro (Prejuízo) atribuído aos não controladores (minoritários) | S43: - | T43: -284 | U43: -284 | V43: -284 | W43: 507 | X43: -1840 | Y43: -773 | Z43: 0 | AA43: 0 | AB43: 0 | AC43: 0 | AD43: 0 | AE43: 0
B45: Earnings (loss) per share – Basic | C45: 0.0301 | D45: =-0.078 -> -0.078 | E45: -0.014345982 | F45: -0.016031503 | G45: -0.0096774851 | H45: -0.103 | I45: -0.0717 | J45: -0.04768 | K45: -0.0367 | L45: -0.1304 | M45: -0.0492 | N45: -0.2443 | O45: -0.0258 | R45: Resultado por ação - básico | S45: 0.1563 | T45: -0.3838 | U45: -0.0736 | V45: -0.081377273 | W45: -0.050564919 | X45: -0.5557 | Y45: -0.3825 | Z45: -0.25682 | AA45: -0.2015 | AB45: -0.673 | AC45: -0.2501 | AD45: -0.12035 | AE45: -0.1153
B47: Earnings (loss) per share – Diluted | C47: 0.0294 | D47: =-0.078 -> -0.078 | E47: -0.014345982 | F47: -0.016031503 | G47: -0.0096774851 | H47: -0.103 | I47: -0.0717 | J47: -0.04768 | K47: -0.0367 | L47: -0.1304 | M47: -0.0492 | N47: -0.2443 | O47: -0.0258 | R47: Resultado por ação - diluído | S47: 0.1528 | T47: -0.3838 | U47: -0.0736 | V47: -0.081377273 | W47: -0.050564919 | X47: -0.5557 | Y47: -0.3825 | Z47: -0.25682 | AA47: -0.2015 | AB47: -0.673 | AC47: -0.2501 | AD47: -0.12035 | AE47: -0.1153
B49: Weighted average number of outstanding shares – Basic (in thousands of shares) | C49: 4709505 | D49: 4676977 | E49: 4671761 | F49: 4665688.4 | G49: 4660405 | H49: 1602126 | I49: 1379271 | J49: 1357132 | K49: 1347258 | L49: 1315578 | M49: 1309861 | N49: 1304431 | O49: 1296708 | R49: Número médio ponderado de ações em circulação - básica (em milhares de ações) | S49: 4709505 | T49: 4676977 | U49: 4671761 | V49: 4665688.4 | W49: 4660405 | X49: 1602126 | Y49: 1379271 | Z49: 1357132 | AA49: 1347258 | AB49: 1315578 | AC49: 1309861 | AD49: 1304431 | AE49: 1296708
B51: Weighted average number of outstanding shares – Diluted (in thousands of shares) | C51: 4808200 | D51: 4676977 | E51: 4671761 | F51: 4665688.4 | G51: 4660405 | H51: 1602126 | I51: 1379271 | J51: 1357132 | K51: 1347258 | L51: 1315578 | M51: 1309861 | N51: 1304431 | O51: 1296708 | R51: Número médio ponderado de ações em circulação - diluída (em milhares de ações) | S51: 4808200 | T51: 4676977 | U51: 4671761 | V51: 4665688.4 | W51: 4660405 | X51: 1602126 | Y51: 1379271 | Z51: 1357132 | AA51: 1347258 | AB51: 1315578 | AC51: 1309861 | AD51: 1304431 | AE51: 1296708

Sheet Financial Position (Balanços Pa
B2: Nu Holdings Ltd. | P2: Nu Holdings Ltd.
B3: Consolidated Statement of Financial Position | P3: Balanços Patrimoniais Consolidados
B4: Amounts in thousands of US$ | P4: Valores em R$ mil
B5: Back to Contents | P5: Retornar ao Índice
C10: 31/3/2023 | D10: 44926 | E10: 44834 | F10: 44742 | G10: 44651 | H10: 44561 | I10: 44469 | J10: 44377 | K10: 44286 | L10: 44196 | M10: 43830 | Q10: 31/3/2023 | R10: 44926 | S10: 44834 | T10: 44742 | U10: 44651 | V10: 44561 | W10: 44469 | X10: 44377 | Y10: 44286 | Z10: 44196 | AA10: 43830
C11: US$ | D11: US$ | E11: US$ | F11: US$ | G11: US$ | H11: US$ | I11: US$ | J11: US$ | K11: US$ | L11: US$ | M11: US$ | Q11: R$ | R11: R$ | S11: R$ | T11: R$ | U11: R$ | V11: R$ | W11: R$ | X11: R$ | Y11: R$ | Z11: R$ | AA11: R$
B12: Assets | P12: Ativo
B13: Cash and cash equivalents | C13: 4310496 | D13: 4172316 | E13: 3692793 | F13: 3701020 | G13: 2968622 | H13: 2705675 | I13: 1996725 | J13: 2662467 | K13: 2200663 | L13: 2343780 | M13: 1246566 | P13: Caixa e equivalentes de caixa | Q13: 21824472 | R13: 22031497 | S13: 19998320 | T13: 19455522 | U13: 14076315 | V13: 15086303 | W13: 10867975 | X13: 13231396 | Y13: 12397875 | Z13: 12184140 | AA13: 5024160
B14: Financial assets at fair value through profit or loss | C14: 109033 | D14: 133643 | E14: 780827 | F14: 967329 | G14: 1037055 | H14: 918332 | I14: 4780936 | J14: 5390216 | K14: 4405577 | L14: 4378118 | M14: 2400691 | P14: Ativos financeiros ao valor justo por meio do resultado | Q14: 552045 | R14: 705689 | S14: 4228569 | T14: 5085055 | U14: 4917403 | V14: 5120436 | W14: 26022157 | X14: 26787217 | Y14: 24819700 | Z14: 22759646 | AA14: 9675744
B15: Securities | C15: 94038 | D15: 91853 | E15: 740972 | F15: 856994 | G15: 817443 | H15: 815962 | I15: 4680014 | J15: 5343289 | K15: 4356451 | L15: 4287277 | M15: 2237673 | P15: Títulos e valores mobiliários | Q15: 476124 | R15: 485021 | S15: 4012734 | T15: 4505046 | U15: 3876069 | V15: 4549641 | W15: 25472848 | X15: 26554009 | Y15: 24542938 | Z15: 22287409 | AA15: 9018717
B16: Derivative financial instruments | C16: 14686 | D16: 41485 | E16: 39552 | F16: 109934 | G16: 209439 | H16: 101318 | I16: 89543 | J16: 5845 | K16: 34 | L16: 80 | M16: 241 | P16: Instrumentos financeiros derivativos | Q16: 74357 | R16: 219057 | S16: 214194 | T16: 577901 | U16: 993097 | V16: 564929 | W16: 487374 | X16: 29047 | Y16: 192 | Z16: 416 | AA16: 971
B17: Collateral for credit card operations | C17: 309 | D17: 305 | E17: 303 | F17: 401 | G17: 10173 | H17: 1052 | I17: 11379 | J17: 41082 | K17: 49092 | L17: 90761 | M17: 162777 | P17: Garantias para operações de cartão de crédito | Q17: 1564 | R17: 1611 | S17: 1641 | T17: 2108 | U17: 48237 | V17: 5866 | W17: 61935 | X17: 204161 | Y17: 276570 | Z17: 471821 | AA17: 656056
B18: Financial assets at fair value through other comprehensive income | C18: 7916143 | D18: 9947138 | E18: 8931961 | F18: 8850741 | G18: 9260432 | H18: 8163428 | I18: 1837715 | J18: 348518 | K18: 0 | L18: 0 | M18: 0 | P18: Ativos financeiros a valor justo através de outros resultados abrangentes | Q18: 40080224 | R18: 52524867 | S18: 48371035 | T18: 46526575 | U18: 43910190 | V18: 45517642 | W18: 10002499 | X18: 1731995 | Y18: 0 | Z18: 0 | AA18: 0
B19: Securities | C19: 7916143 | D19: 9947138 | E19: 8931961 | F19: 8850741 | G19: 9260432 | H19: 8163428 | I19: 1837715 | J19: 348518 | K19: 0 | L19: 0 | M19: 0 | P19: Títulos e valores mobiliários | Q19: 40080224 | R19: 52524867 | S19: 48371035 | T19: 46526575 | U19: 43910190 | V19: 45517642 | W19: 10002499 | X19: 1731995 | Y19: 0 | Z19: 0 | AA19: 0
B20: Financial assets at amortized cost | C20: 15029584 | D20: 13684484 | E20: 10908864 | F20: 10141709 | G20: 9571139 | H20: 6982835 | I20: 5335867 | J20: 4634392 | K20: 3172369 | L20: 3150013 | M20: 2923676 | P20: Ativos financeiros ao custo amortizado | Q20: 76096287 | R20: 72259550 | S20: 59076952 | T20: 53312935 | U20: 45383469 | V20: 38934892 | W20: 29042591 | X20: 23031075 | Y20: 17872172 | Z20: 16375342 | AA20: 11783585
B21: Credit card receivables | C21: 9158452 | D21: 8233072 | E21: 6987948 | F21: 6478470 | G21: 6234824 | H21: 4780520 | I21: 4061505 | J21: 3819891 | K21: 2787813 | L21: 2908907 | M21: 2786524 | P21: Recebíveis de cartões de crédito | Q21: 46370158 | R21: 43473913 | S21: 37843232 | T21: 34056021 | U21: 29563665 | V21: 26655223 | W21: 22106366 | X21: 18983330 | Y21: 15705700 | Z21: 15121953 | AA21: 11230808
B22: Loans to customers | C22: 2020191 | D22: 1673440 | E22: 1603105 | F22: 1675776 | G22: 1667517 | H22: 1194814 | I22: 792736 | J22: 519686 | K22: 264542 | L22: 174694 | M22: 58024 | P22: Empréstimos para clientes | Q22: 10228922 | R22: 8836433 | S22: 8681615 | T22: 8809219 | U22: 7906865 | V22: 6662044 | W22: 4314783 | X22: 2582632 | Y22: 1490350 | Z22: 908146 | AA22: 233860
B23: Compulsory and other deposits at central banks | C23: 2671668 | D23: 2778019 | E23: 1860438 | F23: 1552139 | G23: 1333427 | H23: 938659 | I23: 422649 | J23: 265465 | K23: 98694 | L23: 43542 | M23: 0 | P23: Depósitos compulsórios e outros em bancos centrais | Q23: 13526922 | R23: 14669052 | S23: 10075202 | T23: 8159284 | U23: 6322711 | V23: 5233775 | W23: 2300436 | X23: 1319255 | Y23: 556012 | Z23: 226353 | AA23: 0
B24: Interbank transactions | C24: - | D24: 0 | E24: 0 | F24: 0 | G24: 0 | H24: 0 | I24: 19749 | J24: 4451 | K24: 1424 | L24: 0 | M24: 91 | P24: Transações interbancárias | Q24: - | R24: 0 | S24: 0 | T24: 0 | U24: 0 | V24: 0 | W24: 107492 | X24: 22120 | Y24: 8022 | Z24: 0 | AA24: 367
B25: Other receivables | C25: 1076681 | D25: 521670 | E25: 381782 | F25: 374188 | G25: 285632 | H25: 50349 | P25: Outros recebíveis | Q25: 5451344 | R25: 2754626 | S25: 2067540 | T25: 1967031 | U25: 1354380 | V25: 280737
B26: Other financial assets | C26: 102592 | D26: 478283 | E26: 75591 | F26: 61136 | G26: 49739 | H26: 18493 | I26: 39228 | J26: 24899 | K26: 19896 | L26: 22870 | M26: 79037 | P26: Outros ativos financeiros ao custo amortizado | Q26: 519434 | R26: 2525526 | S26: 409363 | T26: 321380 | U26: 235848 | V26: 103113 | W26: 213514 | X26: 123738 | Y26: 112088 | Z26: 118890 | AA26: 318550
B27: Other assets | C27: 500225 | D27: 541903 | E27: 388604 | F27: 331383 | G27: 288115 | H27: 232915 | I27: 171170 | J27: 176253 | K27: 133004 | L27: 123495 | M27: 67931 | P27: Outros ativos | Q27: 2532689 | R27: 2861465 | S27: 2104485 | T27: 1742014 | U27: 1366155 | V27: 1298686 | W27: 931661 | X27: 875907 | Y27: 749305 | Z27: 641990 | AA27: 273790
B28: Deferred tax assets | C28: 964179 | D28: 811050 | E28: 700706 | F28: 598917 | G28: 565310 | H28: 360752 | I28: 328458 | J28: 266890 | K28: 178552 | L28: 125131 | M28: 94198 | P28: Ativos fiscais diferidos | Q28: 4881735 | R28: 4282668 | S28: 3794673 | T28: 3148387 | U28: 2680530 | V28: 2011481 | W28: 1787764 | X28: 1326337 | Y28: 1005908 | Z28: 650494 | AA28: 379656
B29: Right-of-use assets | C29: 16811 | D29: 18982 | E29: 17301 | F29: 21888 | G29: 18994 | H29: 6426 | I29: 7454 | J29: 9142 | K29: 8977 | L29: 10660 | M29: 17195 | P29: Ativos de direito de uso | Q29: 85116 | R29: 100233 | S29: 93694 | T29: 115061 | U29: 90064 | V29: 35830 | W29: 40571 | X29: 45432 | Y29: 50574 | Z29: 55416 | AA29: 69303
B30: Property, plant and equipment | C30: 30131 | D30: 27482 | E30: 20609 | F30: 18658 | G30: 18200 | H30: 14109 | I30: 12106 | J30: 12690 | K30: 8952 | L30: 9850 | M30: 8667 | P30: Imobilizado | Q30: 152556 | R30: 145116 | S30: 111608 | T30: 98081 | U30: 86299 | V30: 78669 | W30: 65892 | X30: 63064 | Y30: 50433 | Z30: 51205 | AA30: 34931
B31: Intangible assets | C31: 215303 | D31: 182164 | E31: 167989 | F31: 147432 | G31: 120563 | H31: 72337 | I31: 61847 | J31: 59240 | K31: 12162 | L31: 12372 | M31: 1110 | P31: Ativo intangível | Q31: 1090101 | R31: 961899 | S31: 909744 | T31: 775021 | U31: 571674 | V31: 403337 | W31: 336627 | X31: 306037 | Y31: 68517 | Z31: 64316 | AA31: 4474
B32: Goodwill | C32: 397486 | D32: 397397 | E32: 397334 | F32: 409604 | G32: 409573 | H32: 401872 | I32: 393820 | J32: 391706 | K32: 831 | L32: 831 | M32: - | P32: Ágio | Q32: 2084104 | R32: 2083644 | S32: 2083315 | T32: 2147461 | U32: 2147379 | V32: 2102736 | W32: 2058834 | X32: 2047783 | Y32: 4682 | Z32: 4320 | AA32: -
B33: Total assets | C33: 29489391 | D33: 29916559 | E33: 26006988 | F33: 25188681 | G33: 24258003 | H33: 19858681 | I33: 14926098 | J33: 13951514 | K33: 10121087 | L33: 10154250 | M33: 6760034 | P33: Total do ativo | Q33: 149379104 | R33: 157956628 | S33: 140772395 | T33: 132406112 | U33: 115229478 | V33: 110590012 | W33: 81156571 | X33: 69446243 | Y33: 57019166 | Z33: 52786869 | AA33: 27245643
B35: Liabilities | P35: Passivo
B36: Financial liabilities at fair value through profit or loss | C36: 157435 | D36: 218174 | E36: 69211 | F36: 121978 | G36: 200505 | H36: 102380 | I36: 99169 | J36: 14884 | K36: 110787 | L36: 90796 | M36: 24125 | P36: Passivos financeiros ao valo justo por meio do resultado | Q36: 797109 | R36: 1152047 | S36: 374813 | T36: 641214 | U36: 950734 | V36: 570851 | W36: 539767 | X36: 73967 | Y36: 624140 | Z36: 472003 | AA36: 97233
B37: Derivative financial instruments | C37: 10344 | D37: 9425 | E37: 4048 | F37: 86511 | G37: 177079 | H37: 87278 | I37: 86638 | J37: 122 | K37: 62216 | L37: 75304 | M37: 2041 | P37: Instrumentos financeiros derivativos | Q37: 52373 | R37: 49768 | S37: 21922 | T37: 454771 | U37: 839655 | V37: 486645 | W37: 471562 | X37: 606 | Y37: 350506 | Z37: 391468 | AA37: 8226
B38: Instruments eligible as capital | C38: 2932 | D38: 11507 | E38: 19099 | F38: 18554 | G38: 20226 | H38: 12056 | I38: 12531 | J38: 14762 | K38: 13063 | L38: 15492 | M38: 22084 | P38: Instrumentos elegíveis a capital | Q38: 14845 | R38: 60762 | S38: 103431 | T38: 97535 | U38: 95906 | V38: 67222 | W38: 68205 | X38: 73361 | Y38: 73593 | Z38: 80535 | AA38: 89007
B39: Repurchase agreements | C39: 144159 | D39: 197242 | E39: 46064 | F39: 16913 | G39: 3200 | H39: 3046 | I39: 0 | J39: - | K39: 35508 | P39: Compromisso de recompra | Q39: 729891 | R39: 1041517 | S39: 249460 | T39: 88908 | U39: 15173 | V39: 16984 | W39: 0 | X39: - | Y39: 200041 | Z39: 0 | AA39: 0
B40: Financial liabilities at amortized cost | C40: 23280670 | D40: 23448892 | E40: 20402552 | F40: 19695082 | G40: 18665367 | H40: 14706713 | I40: 12378683 | J40: 11602615 | K40: 8947550 | L40: 9421710 | M40: 5972989 | P40: Passivos financeiros ao custo amortizado | Q40: =SUM(Q41:Q43) -> 117872361 | R40: 123819529 | S40: 110490020 | T40: 103533107 | U40: 88505571 | V40: 82001690 | W40: 67375934 | X40: 57660355 | Y40: 50407813 | Z40: 48978760 | AA40: 24073535
B41: Deposits | C41: 15757663 | D41: 15808541 | E41: 14040157 | F41: 13293235 | G41: 12596927 | H41: 9667300 | I41: 8089835 | J41: 7505684 | K41: 5461652 | L41: 5584862 | M41: 2693158 | P41: Depósitos | Q41: 79782624 | R41: 83475420 | S41: 76034470 | T41: 69879878 | U41: 59730849 | V41: 53902931 | W41: 44032163 | X41: 37300247 | Y41: 30769309 | Z41: 29032905 | AA41: 10854504
B42: Payables to network | C42: 6871826 | D42: 7054783 | E42: 5894436 | F42: 5930966 | G42: 5920795 | H42: 4882159 | I42: 4127691 | J42: 3990411 | K42: 2982547 | L42: 3331258 | M42: 2976505 | P42: Valores a repassar à rede | Q42: 34792742 | R42: 37252076 | S42: 31921318 | T42: 31177902 | U42: 28074634 | V42: 27221942 | W42: 22466609 | X42: 19830747 | Y42: 16802775 | Z42: 17317545 | AA42: 11996506
B43: Borrowings and financing | C43: 651181 | D43: 585568 | E43: 467959 | F43: 470881 | G43: 147645 | H43: 147243 | I43: 134398 | J43: 59165 | K43: 103220 | L43: 97454 | M43: 133401 | P43: Empréstimos e financiamentos | Q43: 3296995 | R43: 3092033 | S43: 2534232 | T43: 2475327 | U43: 700088 | V43: 820998 | W43: 731515 | X43: 294026 | Y43: 581511 | Z43: 506615 | AA43: 537659
B44: Securitized borrowings | C44: - | D44: - | E44: - | F44: 0 | G44: 0 | H44: 10011 | I44: 26759 | J44: 47355 | K44: 57681 | L44: 79742 | M44: 169925 | P44: Empréstimos securitizados | Q44: - | R44: - | S44: - | T44: 0 | U44: 0 | V44: 55819 | W44: 145647 | X44: 235335 | Y44: 324957 | Z44: 414539 | AA44: 684866
B45: Senior preferred shares | C45: - | D45: 0 | E45: 0 | F45: - | G45: - | H45: - | I45: - | J45: - | K45: 342450 | L45: 328394 | M45: 0 | P45: Ações preferenciais seniores | Q45: - | R45: 0 | S45: 0 | T45: 0 | U45: 0 | V45: - | W45: - | X45: - | Y45: 1929261 | Z45: 1707156 | AA45: -
B46: Salaries, allowances and social security contributions | C46: 101288 | D46: 90587 | E46: 107547 | F46: 88070 | G46: 115599 | H46: 97909 | I46: 68506 | J46: 53995 | K46: 35740 | L46: 25848 | M46: 11238 | P46: Salários, abonos e encargos sociais | Q46: 512831 | R46: 478336 | S46: 582421 | T46: 462966 | U46: 548136 | V46: 545921 | W46: 372871 | X46: 268334 | Y46: 201348 | Z46: 134371 | AA46: 45294
B47: Tax liabilities | C47: 259223 | D47: 511017 | E47: 323375 | F47: 219905 | G47: 140797 | H47: 241197 | I47: 166326 | J47: 106794 | K47: 40162 | L47: 30782 | M47: 12430 | P47: Obrigações fiscais | Q47: 1312472 | R47: 2698374 | S47: 1751237 | T47: 1155997 | U47: 667617 | V47: 1344866 | W47: 905296 | X47: 530723 | Y47: 226258 | Z47: 160020 | AA47: 50098
B48: Lease liabilities | C48: 19299 | D48: 20353 | E48: 18861 | F48: 25021 | G48: 20319 | H48: 7621 | I48: 8748 | J48: 10578 | K48: 10244 | L48: 12014 | M48: 18701 | P48: Passivo de arrendamentos | Q48: 97713 | R48: 107472 | S48: 102142 | T48: 131530 | U48: 96347 | V48: 42493 | W48: 47614 | X48: 52568 | Y48: 57712 | Z48: 62455 | AA48: 75373
B49: Provision for lawsuits and administrative proceedings | C49: 19988 | D49: 17947 | E49: 17307 | F49: 17288 | G49: 18899 | H49: 18082 | I49: 16223 | J49: 17569 | K49: 15537 | L49: 16469 | M49: 20952 | P49: Provisão para processos judiciais e administrativos | Q49: 101201 | R49: 94767 | S49: 93726 | T49: 90880 | U49: 89613 | V49: 100822 | W49: 88300 | X49: 87311 | Y49: 87531 | Z49: 85614 | AA49: 84445
B50: Deferred income | C50: 47122 | D50: 41688 | E50: 36450 | F50: 36595 | G50: 37141 | H50: 30657 | I50: 29419 | J50: 31619 | K50: 26274 | L50: 25965 | M50: 21154 | P50: Receita diferida | Q50: 238583 | R50: 220129 | S50: 197395 | T50: 192373 | U50: 176111 | V50: 170937 | W50: 160125 | X50: 157134 | Y50: 148020 | Z50: 134979 | AA50: 85259
B51: Deferred tax liabilities | C51: 47961 | D51: 41118 | E51: 42342 | F51: 43283 | G51: 45659 | H51: 29334 | I51: 81440 | J51: 52279 | K51: 38135 | L51: 8741 | M51: 698 | P51: Passivo fiscal diferido | Q51: 242831 | R51: 217119 | S51: 229303 | T51: 227530 | U51: 216501 | V51: 163561 | W51: 443270 | X51: 259806 | Y51: 214841 | Z51: 45440 | AA51: 2813
B52: Other liabilities | C52: 347884 | D52: 636000 | E52: 236661 | F52: 203300 | G52: 223135 | H52: 182247 | I52: 172181 | J52: 124086 | K52: 92811 | L52: 83814 | M52: 65496 | P52: Outros passivos | Q52: 1761371 | R52: 3358334 | S52: 1281638 | T52: 1068707 | U52: 1058039 | V52: 1016173 | W52: 937159 | X52: 616658 | Y52: 522864 | Z52: 435707 | AA52: 263977
B53: Total liabilities | C53: 24280870 | D53: 25025776 | E53: 21254306 | F53: 20450522 | G53: 19467421 | H53: 15416140 | I53: 13020695 | J53: 12014419 | K53: 9317240 | L53: 9716139 | M53: 6147783 | P53: Total do passivo | Q53: 122936472 | R53: 132146107 | S53: 115102695 | T53: 107504304 | U53: 92308669 | V53: 85957314 | W53: 70870336 | X53: 59706856 | Y53: 52490527 | Z53: 50509349 | AA53: 24778027
B55: Equity | P55: Patrimônio líquido
B56: Share capital | C56: 83 | D56: 83 | E56: 83 | F56: 83 | G56: 83 | H56: 83 | I56: 81 | J56: 81 | K56: 48 | L56: 45 | M56: 45 | P56: Capital social | Q56: 350 | R56: 350 | S56: 350 | T56: 350 | U56: 350 | V56: 350 | W56: 339 | X56: 339 | Y56: 166 | Z56: 150 | AA56: 150
B57: Share premium reserve | C57: 4965793 | D57: 4963774 | E57: 4963187 | F57: 4962573 | G57: 4960557 | H57: 4678585 | I57: 2113501 | J57: 2112245 | K57: 1038361 | L57: 638007 | M57: 631246 | P57: Reserva de prêmio na subscrição de ações | Q57: 26198856 | R57: 26188373 | S57: 26185221 | T57: 26181874 | U57: 26171833 | V57: 24569729 | W57: 10244829 | X57: 10238243 | Y57: 4543415 | Z57: 2352793 | AA57: 2317886
B58: Accumulated gain (losses) | C58: 257090 | D58: 64577 | E58: -45876 | F58: -95911 | G58: -116805 | H58: -128409 | I58: -108893 | J58: -104818 | K58: -117288 | L58: -102441 | M58: 28189 | P58: Prejuízos acumulados | Q58: 1254582 | R58: 254978 | S58: -318069 | T58: -576599 | U58: -680932 | V58: -741563 | W58: -635835 | X58: -614236 | Y58: -682871 | Z58: -601432 | AA58: 73011
B59: Other comprehensive income (loss) | C59: -14445 | D59: -137651 | E59: -164712 | F59: -128586 | G59: -54790 | H59: -109227 | I59: -101016 | J59: -70413 | K59: -117274 | L59: -97500 | M59: -47229 | P59: Outros resultados abrangentes | Q59: -1011701 | R59: -633180 | S59: -197802 | T59: -703817 | U59: -2578730 | V59: 796039 | W59: 667674 | X59: 115041 | Y59: 667929 | Z59: 526009 | AA59: 76569
B60: Equity attributable to shareholders of the parent company | C60: 5208521 | D60: 4890783 | E60: 4752682 | F60: 4738159 | G60: 4789045 | H60: 4441032 | I60: 1903673 | J60: 1937095 | K60: 803847 | L60: 438111 | M60: 612251 | P60: Total do patrimônio líquido de controladores | Q60: 26442087 | R60: =SUM(R56:R59) -> 25810521 | S60: 25669700 | T60: 24901808 | U60: 22912521 | V60: 24624555 | W60: 10277007 | X60: 9739387 | Y60: 4528639 | Z60: 2277520 | AA60: 2467616
B61: Equity attributable to non-controlling interests | C61: - | D61: - | E61: 0 | F61: 0 | G61: 1537 | H61: 1509 | I61: 1730 | J61: 0 | K61: 0 | L61: 0 | M61: 0 | P61: Patrimônio líquido de não controladores | Q61: - | R61: - | S61: 0 | T61: 0 | U61: 8289 | V61: 8143 | W61: 9228 | Y61: 0 | Z61: 0 | AA61: 0
B62: Total equity | C62: 5208521 | D62: 4890783 | E62: 4752682 | F62: 4738159 | G62: 4790582 | H62: 4442541 | I62: 1905403 | J62: 1937095 | K62: 803847 | L62: 438111 | M62: 612251 | P62: Total do patrimônio líquido | Q62: 26442087 | R62: 25810521 | S62: 25669700 | T62: 24901808 | U62: 22920810 | V62: 24632698 | W62: 10286235 | X62: 9739387 | Y62: 4528639 | Z62: 2277520 | AA62: 2467616
B64: Total liabilities and equity | C64: 29489391 | D64: 29916559 | E64: 26006988 | F64: 25188681 | G64: 24258003 | H64: 19858681 | I64: 14926098 | J64: 13951514 | K64: 10121087 | L64: 10154250 | M64: 6760034 | P64: Total do passivo e patrimônio líquido | Q64: 149378559 | R64: 157956628 | S64: 140772395 | T64: 132406112 | U64: 115229478 | V64: 110590012 | W64: 81156571 | X64: 69446243 | Y64: 57019166 | Z64: 52786869 | AA64: 27245643

Sheet Cash Flow (fluxo de caixa)
B2: Nu Holdings Ltd. | R2: Nu Holdings Ltd.
B3: Consolidated Statement of Cash Flow | R3: Demonstrações Consolidadas do Fluxo de Caixa
B4: Amounts in thousands of US$ | R4: Valores em R$ mil
B5: Back to Contents | R5: Retornar ao Índice
C10: 31/3/2023 | D10: 44926 | E10: 44834 | F10: 44742 | G10: 44651 | H10: 44561 | I10: 44469 | J10: 44377 | K10: 44286 | L10: 44196 | M10: 44104 | N10: 44012 | O10: 43921 | P10: 43830 | S10: 31/3/2023 | T10: 44926 | U10: 44834 | V10: 44742 | W10: 44651 | X10: 44561 | Y10: 44469 | Z10: 44377 | AA10: 44286 | AB10: 44196 | AC10: 44104 | AD10: 44012 | AE10: 43921 | AF10: 43830
C11: US$ | D11: US$ | E11: US$ | F11: US$ | G11: US$ | H11: US$ | I11: US$ | J11: US$ | K11: US$ | L11: US$ | M11: US$ | N11: US$ | O11: US$ | P11: US$ | S11: R$ | T11: R$ | U11: R$ | V11: R$ | W11: R$ | X11: R$ | Y11: R$ | Z11: R$ | AA11: R$ | AB11: R$ | AC11: R$ | AD11: R$ | AE11: R$ | AF11: R$
B12: Cash flows from operating activities | R12: Fluxos de caixa das atividades operacionais
B13: Reconciliation of profit (loss) to net cash flows from operating activities: | R13: Reconciliação do lucro (prejuízo) com os fluxos de caixa líquidos das atividades operacionais:
B14: Profit (Loss) for the period/year | C14: 141751 | D14: -364634 | E14: -67021 | F14: -74854 | G14: -45004 | H14: -165334 | I14: -99060 | J14: -64703 | K14: -49483 | L14: -171491 | M14: -64434 | N14: -31872 | O14: -33433 | P14: -92531 | R14: Lucro (Prejuízo) do período/exercício | S14: 736027 | T14: -1883444 | U14: -344133 | V14: -379965 | W14: -235146 | X14: -892192 | Y14: -528356 | Z14: -348535 | AA14: -271443 | AB14: -885408 | AC14: -327647 | AD14: -156981 | AE14: -149530 | AF14: -364960
B15: Adjustments: | R15: Ajustes:
B16: Depreciation and amortization | C16: 13179 | D16: 35581 | E16: 25699 | F16: 18088 | G16: 7655 | H16: 17339 | I16: 10896 | J16: 5242 | K16: 2507 | L16: 7428 | M16: 3783 | N16: 2893 | O16: 560 | P16: 5073 | R16: Depreciação e amortização | S16: 68431 | T16: 183785 | U16: 131957 | V16: 91816 | W16: 39997 | X16: 93566 | Y16: 58116 | Z16: 28237 | AA16: 13752 | AB16: 38351 | AC16: 19237 | AD16: 14249 | AE16: 2505 | AF16: 20009
B17: Credit loss allowance expenses | C17: 491937 | D17: 1440922 | E17: 1009827 | F17: 625185 | G17: 279489 | H17: 503679 | I17: 299404 | J17: 165815 | K17: 77210 | L17: 187790 | M17: 126184 | N17: 87430 | O17: 64181 | P17: 193967 | R17: Despesas com provisão para perdas de crédito | S17: 2554334 | T17: 7442795 | U17: 5185159 | V17: 3173502 | W17: 1460330 | X17: 2718002 | Y17: 1596931 | Z17: 893196 | AA17: 423543 | AB17: 969560 | AC17: 641646 | AD17: 430627 | AE17: 287050 | AF17: 765045
B18: Deferred income taxes | C18: -103986 | D18: -417612 | E18: -322255 | F18: -212710 | G18: -121699 | H18: -224654 | I18: -132732 | J18: -78958 | K18: -35392 | L18: -44025 | M18: -24079 | N18: -18613 | O18: -19404 | P18: -40340 | R18: Tributos diferidos | S18: -539937 | T18: -2157091 | U18: -1654683 | V18: -1079737 | W18: -635877 | X18: -1212300 | Y18: -707953 | Z18: -425323 | AA18: -194147 | AB18: -227301 | AC18: -122442 | AD18: -91676 | AE18: -86785 | AF18: -159109
B19: Customer program | C19: - | D19: - | E19: 0 | F19: 0 | G19: 0 | H19: 11180 | I19: 0 | J19: 0 | K19: 0 | L19: 0 | M19: 0 | N19: 0 | O19: 0 | P19: 0 | R19: Programa de clientes | S19: - | T19: - | U19: 0 | V19: 0 | W19: 0 | X19: 60331 | Y19: 0 | Z19: 0 | AA19: 0 | AB19: 0 | AC19: 0 | AD19: 0 | AE19: 0 | AF19: 0
B20: Provision for lawsuits and administrative proceedings | C20: 1239 | D20: -1174 | E20: -1382 | F20: -1958 | G20: -2147 | H20: 2818 | I20: 502 | J20: 320 | K20: 338 | L20: 227 | M20: 338 | N20: 154 | O20: 131 | P20: 7386 | R20: Provisão para processos judiciais e administrativos | S20: 6433 | T20: -6062 | U20: -7096 | V20: -9938 | W20: -11218 | X20: 15207 | Y20: 2678 | Z20: 1724 | AA20: 1854 | AB20: 1171 | AC20: 1719 | AD20: 759 | AE20: 585 | AF20: 29134
B21: Unrealized losses (gains) on other investments | C21: 18298 | D21: 848 | E21: -5067 | F21: -5067 | G21: -14055 | H21: -39280 | I21: 0 | J21: 0 | K21: 0 | L21: 0 | M21: 0 | N21: 0 | O21: 0 | P21: 0 | R21: Ganhos (perdas) sobre outros investimentos | S21: 95011 | T21: 4380 | U21: -26018 | V21: -25721 | W21: -50166 | X21: -219018 | Y21: 0 | Z21: 0 | AA21: 0 | AB21: 0 | AC21: 0 | AD21: 0 | AE21: 0 | AF21: 0
B22: Unrealized losses (gains) on financial instruments | C22: 4437 | D22: 17794 | E22: 14063 | F22: 38458 | G22: 13508 | H22: 19338 | I22: 161370 | J22: 95216 | K22: 87090 | L22: 48433 | M22: 13067 | N22: -18584 | O22: -6524 | P22: 1799 | R22: Ganhos (perdas) sobre instrumentos financeiros | S22: 23039 | T22: 91911 | U22: 72209 | V22: 195217 | W22: 70579 | X22: 104354 | Y22: 860699 | Z22: 512900 | AA22: 477741 | AB22: 250060 | AC22: 66446 | AD22: -91533 | AE22: -29178 | AF22: 7096
B23: Interest accrued | C23: 16463 | D23: 32479 | E23: 21877 | F23: 8907 | G23: 3706 | H23: 11077 | I23: 7186 | J23: 4658 | K23: 16946 | L23: 39521 | M23: 22770 | N23: 7185 | O23: 4353 | P23: 17681 | R23: Juros incorridos | S23: 85482 | T23: 167764 | U23: 112332 | V23: 45213 | W23: 19364 | X23: 59775 | Y23: 38328 | Z23: 25091 | AA23: 92960 | AB23: 204045 | AC23: 115785 | AD23: 35388 | AE23: 19469 | AF23: 69737
B24: Share-based payments - Contingency share award (CSA) - termination | C24: - | D24: 355573 | E24: 0 | F24: 0 | G24: 0 | H24: 0 | I24: 0 | J24: 0 | K24: 0 | L24: 0 | M24: 0 | N24: 0 | O24: 0 | P24: 0 | R24: Pagamento baseado em ações - rescisão do prêmio de ação contingente | S24: - | T24: 1836641 | U24: 0 | V24: 0 | W24: 0 | X24: 0 | Y24: 0 | Z24: 0 | AA24: 0 | AB24: 0 | AC24: 0 | AD24: 0 | AE24: 0 | AF24: 0
B25: Share-based payments granted | C25: 57857 | D25: 253203 | E25: 188525 | F25: 135656 | G25: 42100 | H25: 152717 | I25: 79729 | J25: 53512 | K25: 32200 | L25: 35569 | M25: 20157 | N25: 14053 | O25: 7111 | P25: 18511 | R25: Pagamento baseado em ações concedido | S25: 300417 | T25: 1307869 | U25: 968019 | V25: 688606 | W25: 219973 | X25: 848968 | Y25: 401521 | Z25: 288258 | AA25: 176637 | AB25: 183643 | AC25: 102498 | AD25: 69216 | AE25: 31804 | AF25: 73011
B26: Others | C26: - | D26: 8203 | E26: 5879 | F26: 0 | G26: 0 | H26: 0 | I26: 0 | J26: 0 | K26: 0 | L26: 0 | M26: 0 | N26: 0 | O26: 0 | P26: 0 | R26: Outros | S26: - | T26: 42371 | U26: 30182 | V26: 0 | W26: 0 | X26: 0 | Y26: 0 | Z26: 0 | AA26: 0 | AB26: 0 | AC26: 0 | AD26: 0 | AE26: 0 | AF26: 0
C27: 641175 | D27: =SUM(D14:D26) -> 1361183 | E27: 870145 | F27: 531705 | G27: 163553 | H27: 288880 | I27: 327295 | J27: 181102 | K27: 131416 | L27: 103452 | M27: 97786 | N27: 42646 | O27: 16975 | P27: 111546 | S27: 3329237 | T27: =SUM(T14:T26) -> 7030919 | U27: 4467928 | V27: 2698993 | W27: 877836 | X27: 1576693 | Y27: 1721964 | Z27: 975548 | AA27: 720897 | AB27: 534121 | AC27: 497242 | AD27: 210049 | AE27: 75920 | AF27: 439963
B28: Changes in operating assets and liabilities: | R28: Variação de ativos e passivos operacionais:
B29: Securities | C29: 1968358 | D29: -1102864 | E29: -749991 | F29: -773539 | G29: -991777 | H29: -4666792 | I29: -2279875 | J29: -1238495 | K29: -1089592 | L29: -2008861 | M29: -865895 | N29: -178688 | O29: 102672 | P29: -1689547 | R29: Títulos e valores mobiliários | S29: 10220502 | T29: -5696623 | U29: -3850979 | V29: -3926561 | W29: -5182035 | X29: -25183410 | Y29: -12160169 | Z29: -6671400 | AA29: -5977068 | AB29: -10371747 | AC29: -4403076 | AD29: -880108 | AE29: 459200 | AF29: -6663911
B30: Compulsory deposits and others at central banks | C30: 5422915 | D30: -1880347 | E30: -972188 | F30: -635319 | G30: -358253 | H30: -924889 | I30: -386869 | J30: -204739 | K30: -65951 | L30: -43841 | M30: - | N30: 0 | O30: - | P30: - | R30: Depósitos compulsórios em bancos centrais | S30: 28157944 | T30: -9712556 | U30: -4991894 | V30: -3224943 | W30: -1871872 | X30: -4990979 | Y30: -2063443 | Z30: -1102869 | AA30: -361779 | AB30: -226353 | AC30: - | AD30: 0 | AE30: - | AF30: -
B31: Credit card receivables | C31: -7973331 | D31: -5213669 | E31: -3502428 | F31: -2459157 | G31: -1576633 | H31: -2568423 | I31: -1594432 | J31: -1066399 | K31: -608551 | L31: -470227 | M31: 652567 | N31: 366816 | O31: 345824 | P31: -1414489 | R31: Recebíveis de cartão de crédito | S31: -41400724 | T31: -26930164 | U31: -17983917 | V31: -12482927 | W31: -8237907 | X31: -13859981 | Y31: -8504222 | Z31: -5744371 | AA31: -3338260 | AB31: -2427774 | AC31: 3318304 | AD31: 1806712 | AE31: 1546697 | AF31: -5579028
B32: Loans to customers | C32: 374403 | D32: -1889278 | E32: -1548747 | F32: -1145997 | G32: -673860 | H32: -1522217 | I32: -875629 | J32: -426329 | K32: -175395 | L32: -178686 | M32: -27279 | N32: -18514 | O32: -24499 | P32: -63009 | R32: Empréstimos para clientes | S32: 1944050 | T32: -9758688 | U32: -7952351 | V32: -5817195 | W32: -3520919 | X32: -8214340 | Y32: -4670343 | Z32: -2296507 | AA32: -962147 | AB32: -922558 | AC32: -138713 | AD32: -91189 | AE32: -109572 | AF32: -248520
B33: Other credit operations | C33: -541190 | D33: -481824 | E33: -349558 | F33: -335367 | G33: 0 | H33: 0 | I33: 0 | J33: 0 | K33: 0 | L33: 0 | M33: 0 | N33: 0 | O33: 0 | P33: 0 | R33: Outras operações de crédito | S33: -2810075 | T33: -2488766 | U33: -1794875 | V33: -1702356 | W33: 0 | X33: 0 | Y33: 0 | Z33: 0 | AA33: 0 | AB33: 0 | AC33: 0 | AD33: 0 | AE33: 0 | AF33: 0
B34: Interbank transactions | C34: - | D34: 0 | E34: - | F34: 0 | G34: 0 | H34: - | I34: -20153 | J34: -4106 | K34: -1462 | L34: 93 | M34: -5008 | N34: -3142 | O34: 93 | P34: -91 | R34: Transações interbancárias | S34: - | T34: 0 | U34: - | V34: 0 | W34: 0 | X34: 0 | Y34: -107490 | Z34: -22120 | AA34: -8022 | AB34: 480 | AC34: -25466 | AD34: -15476 | AE34: 416 | AF34: -359
B35: Other assets | C35: 406972 | D35: -772415 | E35: -210427 | F35: -145172 | G35: -299995 | H35: -64072 | I35: 19379 | J35: -1353 | K35: -14617 | L35: 78319 | M35: 77888 | N35: 84742 | O35: -17671 | P35: -166173 | R35: Outros ativos | S35: 2113161 | T35: -3989755 | U35: -1080480 | V35: -736908 | W35: -1567474 | X35: -345752 | Y35: 103362 | Z35: -7290 | AA35: -80182 | AB35: 404362 | AC35: 396060 | AD35: 417387 | AE35: -79035 | AF35: -655422
B36: Deposits | C36: -49611 | D36: 6278088 | E36: 4611994 | F36: 3755012 | G36: 2658644 | H36: 4001856 | I36: 2343522 | J36: 1579763 | K36: 1067551 | L36: 2871246 | M36: 1529163 | N36: 773253 | O36: 12212 | P36: 2088793 | R36: Depósitos | S36: -257600 | T36: 32428208 | U36: 23681206 | V36: 19060816 | W36: 13891415 | X36: 21595216 | Y36: 12499643 | Z36: 8509709 | AA36: 5856160 | AB36: 14824243 | AC36: 7775794 | AD36: 3808572 | AE36: 54619 | AF36: 8238617
B37: Payables to network | C37: -178401 | D37: 2221037 | E37: 1067635 | F37: 1086143 | G37: 942565 | H37: 1602485 | I37: 812739 | J37: 608114 | K37: 354124 | L37: 312607 | M37: -510635 | N37: -601255 | O37: -485189 | P37: 1365476 | R37: Valores a repassar à rede | S37: -926329 | T37: 11472322 | U37: 5481985 | V37: 5513370 | W37: 4924902 | X37: 8647490 | Y37: 4334906 | Z37: 3275727 | AA37: 1942582 | AB37: 1613990 | AC37: -2596579 | AD37: -2961415 | AE37: -2170006 | AF37: 5385710
B38: Deferred income | C38: 5299 | D38: 11277 | E38: 6110 | F38: 6149 | G38: 5884 | H38: 4848 | I38: 3525 | J38: 5216 | K38: 5869 | L38: 3621 | M38: -3095 | N38: 1690 | O38: 63 | P38: 10325 | R38: Receita diferida | S38: 27515 | T38: 58249 | U38: 31373 | V38: 31213 | W38: 30744 | X38: 26161 | Y38: 18801 | Z38: 28098 | AA38: 32194 | AB38: 18695 | AC38: -15738 | AD38: 8324 | AE38: 281 | AF38: 40724
B39: Other liabilities | C39: -134691 | D39: 979277 | E39: 423586 | F39: 230430 | G39: 144112 | H39: 417225 | I39: 278819 | J39: 128811 | K39: 111629 | L39: 57841 | M39: 32278 | N39: -1997 | O39: 364 | P39: 52366 | R39: Outros passivos | S39: -699370 | T39: 5058259 | U39: 2174987 | V39: 1169686 | W39: 752985 | X39: 2251471 | Y39: 1487137 | Z39: 693865 | AA39: 612350 | AB39: 298633 | AC39: 164133 | AD39: -9836 | AE39: 1626 | AF39: 206543
B41: Interest paid | C41: -18832 | D41: -30935 | E41: -20295 | F41: -8274 | G41: -5300 | H41: -9062 | I41: -7950 | J41: -6707 | K41: -1189 | L41: -6199 | M41: -4253 | N41: -3524 | O41: -2112.3 | P41: -15603.3 | R41: Juros pagos | S41: -97783 | T41: -159789 | U41: -104209 | V41: -42000 | W41: -27693 | X41: -48901 | Y41: -42403 | Z41: -36128 | AA41: -6525 | AB41: -32004 | AC41: -21627 | AD41: -17357 | AE41: -9446 | AF41: -61543
B42: Income tax paid | C42: -404193 | D42: -297090 | E42: -259605 | F42: -234444 | G42: -202487 | H42: -52314 | I42: -36022 | J42: -24557 | K42: -16102 | L42: -7880 | M42: -6406 | N42: -5787 | O42: -5386.3 | P42: -3457.3 | R42: Tributos sobre o lucro pagos | S42: -2098732 | T42: -1534559 | U42: -1332994 | V42: -1190061 | W42: -1057995 | X42: -282302 | Y42: -192131 | Z42: -132281 | AA42: -88329 | AB42: -40686 | AC42: -32575 | AD42: -28503 | AE42: -24089 | AF42: -13635
B43: Interest received | C43: 575419 | D43: 1573133 | E43: 1160989 | F43: 670462 | G43: 271849 | H43: 563550 | I43: 350460 | J43: 196222 | K43: 79526 | L43: 263035 | M43: 201700 | N43: 147816 | O43: 0 | P43: 0 | R43: Juros recebidos | S43: 2987806 | T43: 8125704 | U43: 5961330 | V43: 3403332 | W43: 1420411 | X43: 3041085 | Y43: 1869249 | Z43: 1056990 | AA43: 436249 | AB43: 1358043 | AC43: 1025645 | AD43: 728052 | AE43: 0 | AF43: 0
B44: Cash flows (used in) generated from operating activities | C44: 94292 | D44: 755573 | E44: 527220 | F44: 542632 | G44: 78302 | H44: -2928925 | I44: -1065191 | J44: -273457 | K44: -222744 | L44: 974520 | M44: 1168811 | N44: 604056 | O44: -56654.6 | P44: 276136.4 | R44: Fluxos de caixa gerado (aplicado) nas atividades operacionais | S44: 489602 | T44: =SUM(T27:T43) -> 3902761 | U44: 2707110 | V44: 2754459 | W44: 432398 | X44: -15787549 | Y44: -5705139 | Z44: -1473029 | AA44: -1221880 | AB44: 5031445 | AC44: 5943404 | AD44: 2975212 | AE44: -253389 | AF44: 1089139
B46: Cash flows from investing activities | R46: Fluxos de caixa das atividades de investimento
B47: Acquisition of property, plant and equipment | C47: -4596 | D47: -20001 | E47: -11396 | F47: -7425 | G47: -4683 | H47: -6025 | I47: -2544 | J47: -2010 | K47: -1779.3 | L47: -3084 | M47: -1738 | N47: -1522 | O47: -245 | P47: -2377 | R47: Aquisição de ativo imobilizado | S47: -23864 | T47: -103311 | U47: -58515 | V47: -37690 | W47: -24469 | X47: -32513 | Y47: -13569 | Z47: -10829 | AA47: -9758 | AB47: -15923 | AC47: -8838 | AD47: -7496 | AE47: -1094 | AF47: -9375
B48: Acquisition of intangible assets | C48: -41919 | D48: -94305 | E48: -75220 | F48: -45611 | G48: -10059 | H48: -22473 | I48: -12579 | J48: -3492 | K48: -3424 | L48: -4902 | M48: -3385 | N48: -1322 | O48: - | P48: -2302 | R48: Aquisição de ativo intangível | S48: -217660 | T48: -487114 | U48: -386232 | V48: -231526 | W48: -52558 | X48: -121271 | Y48: -67093 | Z48: -18810 | AA48: -18780 | AB48: -25308 | AC48: -17212 | AD48: -6512 | AE48: - | AF48: -9080
B49: Acquisition of subsidiary, net of cash acquired | C49: - | D49: -10346 | E49: -10346 | F49: -10346 | G49: -10346 | H49: -114486 | I49: -108993 | J49: -108993 | K49: 0 | L49: -8284 | M49: -8283 | N49: 0 | O49: 0 | P49: - | R49: Aquisição de controlada, líquida do caixa adquirido | S49: - | T49: -58715 | U49: -58715 | V49: -58715 | W49: -58715 | X49: -600097 | Y49: -1045078 | Z49: -569801 | AA49: 0 | AB49: -42770 | AC49: -42770 | AD49: 0 | AE49: 0 | AF49: -
B50: Acquisition of securities - equity instruments | C50: - | D50: -2500 | E50: -2500 | F50: -2500 | G50: -13131 | H50: -11211 | I50: 0 | J50: 0 | K50: 0 | L50: 0 | M50: 0 | N50: 0 | O50: 0 | P50: 0 | R50: Aquisição de títulos e valores mobiliários - ações | S50: - | T50: -12913 | U50: -12837 | V50: -12690 | W50: -68609 | X50: -60498 | Y50: 0 | Z50: 0 | AA50: 0 | AB50: 0 | AC50: 0 | AD50: 0 | AE50: 0 | AF50: 0
B51: Cash flow (used in) generated from investing activities | C51: -46515 | D51: -127152 | E51: -99462 | F51: -65882 | G51: -38219 | H51: -154195 | I51: -124116 | J51: -114495 | K51: -5203.3 | L51: -16270 | M51: -13406 | N51: -2844 | O51: -245 | P51: -4679 | R51: Fluxo de caixa gerado (aplicado) nas atividades de investimento | S51: -241524 | T51: =SUM(T47:T50) -> -662053 | U51: -516299 | V51: -340621 | W51: -204351 | X51: -814379 | Y51: -1125740 | Z51: -599440 | AA51: -28538 | AB51: -84001 | AC51: -68820 | AD51: -14008 | AE51: -1094 | AF51: -18455
B53: Cash flows from financing activities | R53: Fluxos de caixa das atividades de financiamento
B54: Proceeds from senior preferred shares | C54: - | D54: 0 | E54: 0 | F54: 0 | G54: 0 | H54: 0 | I54: - | J54: 0 | K54: 0 | L54: 300000 | M54: 300000 | N54: 300000 | O54: 0 | P54: - | R54: Recursos provenientes de ações preferenciais seniores | S54: - | T54: 0 | U54: 0 | V54: 0 | W54: 0 | X54: - | Y54: 0 | Z54: 0 | AA54: 0 | AB54: 1640280 | AC54: 1640280 | AD54: 1640280 | AE54: 0 | AF54: -
B55: Issuance of preferred shares | C55: - | D55: - | E55: - | F55: 0 | G55: 0 | H55: 800000 | I55: 800000 | J55: 800000 | K55: 400000 | L55: 0 | M55: 0 | N55: 0 | P55: 400001 | R55: Emissão de ações preferenciais | S55: - | T55: 0 | U55: 0 | V55: 0 | W55: 0 | X55: 4276200 | Y55: 4276200 | Z55: 4276200 | AA55: 2188680 | AB55: 0 | AC55: 0 | AD55: 0 | AE55: 0 | AF55: 1525924
B56: Issuance of shares under IPO | C56: - | D56: - | E56: - | F56: 0 | G56: 0 | H56: 2590846 | I56: 0 | J56: 0 | K56: 0 | L56: 0 | M56: 0 | N56: 0 | O56: 0 | P56: 0 | R56: Emissão de ações sob o Programa de Clientes e IPO | S56: - | T56: 0 | U56: 0 | V56: 0 | W56: 0 | X56: 14567906 | Y56: 0 | Z56: 0 | AA56: 0 | AB56: 0 | AC56: 0 | AD56: 0 | AE56: 0 | AF56: 0
B57: Transactions costs from IPO | C57: - | D57: - | E57: - | F57: 0 | G57: 0 | H57: -47545 | I57: 0 | J57: 0 | K57: 0 | L57: 0 | M57: 0 | N57: 0 | O57: 0 | P57: 0 | R57: Custo das transações do IPO | S57: - | T57: 0 | U57: 0 | V57: 0 | W57: 0 | X57: -266189 | Y57: 0 | Z57: 0 | AA57: 0 | AB57: 0 | AC57: 0 | AD57: 0 | AE57: 0 | AF57: 0
B58: Issuance of shares for over-allotment in IPO | C58: - | D58: 247998 | E58: 247998 | F58: 247998 | G58: 247998 | H58: 0 | I58: 0 | J58: 0 | K58: 0 | L58: 0 | M58: 0 | N58: 0 | O58: 0 | P58: 0 | R58: Emissão de ações para lote suplementar | S58: - | T58: 1409918 | U58: 1409918 | V58: 1409918 | W58: 1409918 | X58: 0 | Y58: 0 | Z58: 0 | AA58: 0 | AB58: 0 | AC58: 0 | AD58: 0 | AE58: 0 | AF58: 0
B59: Transactions costs for over-allotment in IPO | C59: - | D59: -3985 | E59: -3985 | F59: -3985 | G59: -3985 | H59: 0 | I59: 0 | J59: 0 | K59: 0 | L59: 0 | M59: 0 | N59: 0 | O59: 0 | P59: 0 | R59: Custos de transação do lote suplementar | S59: - | T59: -22656 | U59: -22656 | V59: -22656 | W59: -22656 | X59: 0 | Y59: 0 | Z59: 0 | AA59: 0 | AB59: 0 | AC59: 0 | AD59: 0 | AE59: 0 | AF59: 0
B60: Proceeds from securitized borrowings | C60: - | E60: 0 | F60: 0 | G60: 0 | H60: 0 | I60: 0 | J60: 0 | K60: 0 | L60: - | M60: 0 | N60: 0 | O60: 0 | P60: 126768 | R60: Recursos provenientes de empréstimos securitizados | S60: - | T60: 0 | U60: 0 | V60: 0 | W60: 0 | X60: 0 | Y60: 0 | Z60: 0 | AA60: 0 | AB60: - | AC60: 0 | AD60: 0 | AE60: 0 | AF60: 499998
B61: Payments of securitized borrowings | C61: - | D61: -10633 | E61: -10633 | F61: -10633 | G61: -10633 | H61: -66403 | I61: -50387 | J61: -33261 | K61: -15873 | L61: -52172 | M61: -28797 | N61: -16058 | O61: -8850 | P61: -16835 | R61: Pagamentos de empréstimos securitizados | S61: - | T61: -54923 | U61: -54597 | V61: -53974 | W61: -55557 | X61: -358331 | Y61: -268749 | Z61: -179167 | AA61: -87073 | AB61: -269365 | AC61: -146433 | AD61: -79092 | AE61: -39582 | AF61: -66401
B62: Proceeds from borrowings and financing | C62: 19713 | D62: 581142 | E62: 353093 | F62: 353878 | G62: 0 | H62: 116349 | I62: 106393 | J62: 26955 | K62: 16568 | L62: 17974 | M62: 0 | N62: 0 | O62: 0 | P62: 160577 | R62: Recursos provenientes de empréstimos e financiamentos | S62: 99809 | T62: 2873961 | U62: 1813027 | V62: 1796320 | W62: 0 | X62: 627854 | Y62: 567468 | Z62: 145198 | AA62: 90885 | AB62: 92800 | AC62: 0 | AD62: 0 | AE62: 0 | AF62: 633348
B63: Payments of borrowings and financing | C63: - | D63: -159983 | E63: -38208 | F63: -38305 | G63: -7767 | H63: -60523 | I63: -61234 | J63: -60244 | K63: -4729 | L63: -27893 | M63: -8697 | N63: -5583 | O63: -4484 | P63: -78185 | R63: Pagamentos de empréstimos e financiamentos | S63: - | T63: -826361 | U63: -196187 | V63: -194440 | W63: -40583 | X63: -326600 | Y63: -326603 | Z63: -324516 | AA63: -25941 | AB63: -144012 | AC63: -44224 | AD63: -27498 | AE63: -20055 | AF63: -308377
B64: Proceeds from debt instruments eligible as capital | C64: - | D64: 0 | E64: 0 | F64: 0 | G64: 0 | H64: 0 | I64: 0 | J64: 0 | K64: 0 | L64: - | M64: 0 | N64: 0 | O64: 0 | P64: 18824.3 | R64: Recursos provenientes de instrumentos de dívida elegíveis a capital | S64: - | T64: 0 | U64: 0 | V64: 0 | W64: 0 | X64: 0 | Y64: 0 | Z64: 0 | AA64: 0 | AB64: - | AC64: 0 | AD64: 0 | AE64: 0 | AF64: 74246
B65: Lease payments | C65: -1858 | D65: -5005 | E65: -3394 | F65: -2416 | G65: -1255 | H65: -4387 | I65: -3326 | J65: -2197 | K65: -1080 | L65: -4568 | M65: -3394 | N65: -2385 | O65: -1311 | P65: -2014 | R65: Pagamentos de arrendamento | S65: -9647 | T65: -25852 | U65: -17429 | V65: -12264 | W65: -6557 | X65: -23674 | Y65: -17740 | Z65: -11835 | AA65: -5927 | AB65: -23583 | AC65: -17258 | AD65: -11747 | AE65: -5865 | AF65: -7944
B66: Exercise of stock options | C66: 2019 | D66: 4505 | E66: 3918 | F66: 3304 | G66: 1288 | H66: 12252 | I66: 7835 | J66: 6579 | K66: 2358 | L66: 6776 | M66: 2765 | N66: 1460 | O66: 542 | P66: 5831.3 | R66: Exercício de opções de ações | S66: 10483 | T66: 23270 | U66: 20118 | V66: 16771 | W66: 6730 | X66: 66115 | Y66: 41790 | Z66: 35439 | AA66: 12935 | AB66: 34984 | AC66: 14060 | AD66: 7191 | AE66: 2423 | AF66: 22999
B67: Shares repurchased | C67: - | D67: 0 | E67: 0 | F67: 0 | G67: 0 | H67: -4607 | I67: -4449 | J67: 0 | K67: -2001.3 | L67: -15 | M67: -16 | N67: -15 | O67: -15 | P67: -3774 | R67: Ações recompradas | S67: - | T67: 0 | U67: 0 | V67: 0 | W67: 0 | X67: -24861 | Y67: 0 | Z67: 0 | AA67: -10977 | AB67: -77 | AC67: -81 | AD67: -74 | AE67: -77 | AF67: -14885
B68: Shares withheld for employee’s taxes | C68: - | D68: 0 | E68: 0 | F68: 0 | G68: 0 | H68: 0 | I68: 0 | J68: 0 | K68: 0 | L68: 0 | M68: 0 | N68: 0 | O68: 0 | P68: - | R68: Ações retidas para impostos de funcionários | S68: - | T68: 0 | U68: 0 | V68: 0 | W68: 0 | X68: 0 | Y68: 0 | Z68: 0 | AA68: 0 | AB68: 0 | AC68: 0 | AD68: 0 | AE68: - | AF68: -
B69: Cash flows (used in) generated from financing activities | C69: 19874 | D69: 654039 | E69: 548789 | F69: 549841 | G69: 225646 | H69: 3340589 | I69: 794832 | J69: 737832 | K69: 395242.7 | L69: 240102 | M69: 261861 | N69: 277419 | O69: -14118 | P69: 611193.6 | R69: Fluxo de caixa gerado (aplicado) nas atividades de financiamento | S69: 100645 | T69: =SUM(T55:T68) -> 3377357 | U69: 2952194 | V69: 2939675 | W69: 1291295 | X69: 18538420 | Y69: 4272366 | Z69: 3941319 | AA69: 2162582 | AB69: 1331027 | AC69: 1446344 | AD69: 1529060 | AE69: -63156 | AF69: 2358908
B70: Change in cash and cash equivalents | C70: 67651 | D70: 1282460 | E70: 976547 | F70: 1026591 | G70: 265729 | H70: 257469 | I70: -394475 | J70: 349880 | K70: 167296 | L70: 1198352 | M70: 1417266 | N70: 878631 | O70: -71017.6 | P70: 882651 | R70: Variação de caixa e equivalentes de caixa | S70: 348723 | T70: =SUM(T69,T51,T44) -> 6618065 | U70: 5143005 | V70: 5353513 | W70: 1519342 | X70: 1936492 | Y70: -2558513 | Z70: 1868850 | AA70: 912164 | AB70: 6278471 | AC70: 7320928 | AD70: 4490264 | AE70: -317639 | AF70: 3429592
B72: Cash and cash equivalents | R72: Caixa e equivalentes de caixa
B73: Cash and cash equivalents - beginning of the period/year | C73: 4172316 | D73: 2705675 | E73: 2705675 | F73: 2705675 | G73: 2705675 | H73: 2343780 | I73: 2343780 | J73: 2343780 | K73: 2343780 | L73: 1246566 | M73: 1246566 | N73: 1246566 | O73: 1246566 | P73: 379207 | R73: Caixa e equivalentes de caixa - início do período/exercício | S73: 22031497 | T73: 15086303 | U73: 15086303 | V73: 15086303 | W73: 15086303 | X73: 12184140 | Y73: 12184140 | Z73: 12184140 | AA73: 12184140 | AB73: 5024160 | AC73: 5024160 | AD73: 5024160 | AE73: 5024160 | AF73: 1469238
B74: Foreign exchange rate changes on cash and cash equivalents | C74: 70529 | D74: 184181 | E74: 10571 | F74: -31246 | G74: -2782 | H74: 104426 | I74: 47420 | J74: -31193 | K74: -310413 | L74: -101138 | M74: -606598 | N74: -217779 | O74: -143046 | P74: -15292 | R74: Variação cambial sobre caixa e equivalentes de caixa | S74: -555748 | T74: 327129 | U74: -230988 | V74: -984294 | W74: -2529330 | X74: 965671 | Y74: 1242348 | Z74: -821594 | AA74: -698429 | AB74: 881509 | AC74: -797834 | AD74: 914575 | AE74: 668581 | AF74: 125330
B75: Cash and cash equivalents - end of the period/year | C75: 4310496 | D75: 4172316 | E75: 3692793 | F75: 3701020 | G75: 2968622 | H75: 2705675 | I75: 1996725 | J75: 2662467 | K75: 2200663 | L75: 2343780 | M75: 2057234 | N75: 1907418 | O75: 1032502 | P75: 1246566 | R75: Caixa e equivalentes de caixa - fim do período/exercício | S75: 21824472 | T75: 22031497 | U75: 19998320 | V75: 19455522 | W75: 14076315 | X75: 15086303 | Y75: 10867975 | Z75: 13231396 | AA75: 12397875 | AB75: 12184140 | AC75: 11547254 | AD75: 10428999 | AE75: 5375102 | AF75: 5024160
B77: Increase (decrease) in cash and cash equivalents | C77: 67651 | D77: 1282460 | E77: 976547 | F77: 1026591 | G77: 265729 | H77: 257469 | I77: -394475 | J77: 349880 | K77: 167296 | L77: 1198352 | M77: 1417266 | N77: 878631 | O77: -71018 | P77: 882651 | R77: Aumento do caixa e equivalentes de caixa | S77: 348723 | T77: 6618065 | U77: 5143005 | V77: 5353513 | W77: 1519342 | X77: 1936492 | Y77: -2558513 | Z77: 1868850 | AA77: 912164 | AB77: 6278471 | AC77: 7320928 | AD77: 4490264 | AE77: -317639 | AF77: 3429592

Sheet Revenue breakdown (Abetura das 
B2: Nu Holdings Ltd. | R2: Nu Holdings Ltd.
B3: Revenue Breakdown | R3: Abertura das Receitas
B4: Amounts in thousands of US$ | R4: Valores em R$ mil
B5: Back to Contents | R5: Retornar ao Índice
E9: 3-MONTH PERIOD ENDED | U9: PERÍODO DE 3 MESES FINDOS EM
C10: 31/03/2023 | D10: 44926 | E10: 44834 | F10: 44742 | G10: 44651 | H10: 44561 | I10: 44469 | J10: 44377 | K10: 44286 | L10: 44196 | M10: 44104 | N10: 44012 | O10: 43921 | S10: 31/03/2023 | T10: 44926 | U10: 44834 | V10: 44742 | W10: 44651 | X10: 44561 | Y10: 44469 | Z10: 44377 | AA10: 44286 | AB10: 44196 | AC10: 44104 | AD10: 44012 | AE10: 43921
C11: US$ | D11: US$ | E11: US$ | F11: US$ | G11: US$ | H11: US$ | I11: US$ | J11: US$ | K11: US$ | L11: US$ | M11: US$ | N11: US$ | O11: US$ | S11: R$ | T11: R$ | U11: R$ | V11: R$ | W11: R$ | X11: R$ | Y11: R$ | Z11: R$ | AA11: R$ | AB11: R$ | AC11: R$ | AD11: R$ | AE11: R$
B12: Interest income – credit card | C12: 447696 | D12: 319232 | E12: 262207 | F12: 243916 | G12: 189520 | H12: 129911 | I12: 94054 | J12: 83075 | K12: 61442 | L12: 48003 | M12: 41569 | N12: 58533 | O12: 69400 | R12: Receita de juros – cartão de crédito | S12: 2324617 | T12: 1790265 | U12: 1370384 | V12: 1091243 | W12: 990242 | X12: 716385 | Y12: 494069 | Z12: 447500 | AA12: 337046 | AB12: 261060 | AC12: 231798 | AD12: 288298 | AE12: 310391
B13: Interest income - lending | C13: 286943 | D13: 259571 | E13: 250443 | F13: 228035 | G13: 194147 | H13: 131477 | I13: 84579 | J13: 47125 | K13: 29520 | L13: 16723 | M13: 8406 | N13: 6234 | O13: 7563 | R13: Receita de juros – empréstimos | S13: 1489923 | T13: 1361344 | U13: 1310690 | V13: 1128620 | W13: 1014418 | X13: 719582 | Y13: 447056 | Z13: 253848 | AA13: 161935 | AB13: 88073 | AC13: 44946 | AD13: 30705 | AE13: 33826
B14: Interest income – other assets at amortized cost | C14: 154163 | D14: 122785 | E14: 129556 | F14: 95449 | G14: 40946 | H14: 24821 | I14: 19512 | J14: 13350 | K14: 8519 | L14: 9982 | M14: 9515 | N14: 9254 | O14: 9082 | R14: Receita de juros – outros ativos ao custo amortizado | S14: 800476 | T14: 642361 | U14: 673223 | V14: 478412 | W14: 213943 | X14: 136532 | Y14: 102912 | Z14: 71913 | AA14: 46732 | AB14: 53710 | AC14: 51310 | AD14: 45580 | AE14: 40619
B15: Interest income – other receivables | C15: 86971 | D15: 78734 | E15: 50162 | F15: 32108 | G15: 0 | H15: 0 | I15: 4469 | J15: 2116 | K15: 0 | L15: 0 | N15: 0 | R15: Receita de juros - outros recebíveis | S15: 451588 | T15: 289153 | U15: 260818 | V15: 281663 | W15: 0 | X15: 0 | Y15: 23652 | Z15: 11398 | AA15: 0 | AB15: 0 | AC15: 0 | AD15: 0 | AE15: 0
B16: Interest income and gains (losses) on financial instruments at fair value | C16: 279681 | D16: 315187 | E16: 294880 | F16: 253505 | G16: 194830 | H16: 153341 | I16: 92344 | J16: 39227 | K16: 27864 | L16: 14947 | M16: 10650 | N16: 17863 | O16: 45198 | R16: Ganhos (perdas) sobre instrumentos financeiros ao valor justo | S16: 1452216 | T16: 1650777 | U16: 1540393 | V16: 1257806 | W16: 1017987 | X16: 837455 | Y16: 488980 | Z16: 211304 | AA16: 152851 | AB16: 82920 | AC16: 64222 | AD16: 87981 | AE16: 202148
B17: Financial assets at fair value | C17: 271194 | D17: 319686 | E17: 308569 | F17: 264464 | G17: 194900 | H17: 152968 | I17: 92053 | J17: 38460 | K17: 25715 | L17: 12024 | M17: 11483 | N17: 17843 | O17: 43469 | R17: Ativos financeiros ao valor justo | S17: 1408148 | T17: 1674772 | U17: 1611329 | V17: 1313424 | W17: 1018353 | X17: 835241 | Y17: 487582 | Z17: 207172 | AA17: 141062 | AB17: 67757 | AC17: 68178 | AD17: 87883 | AE17: 194415
B18: Other | C18: 8487 | D18: -4499 | E18: -13689 | F18: -10959 | G18: -70 | H18: 373 | I18: 291 | J18: 767 | K18: 2149 | L18: 2923 | M18: -833 | N18: 20 | O18: 1729 | R18: Outros | S18: 44068 | T18: -23995 | U18: -70936 | V18: -55618 | W18: -366 | X18: 2214 | Y18: 1398 | Z18: 4132 | AA18: 11789 | AB18: 15163 | AC18: -3956 | AD18: 98 | AE18: 7733
B19: Total interest income and gains (losses) on financial instruments | C19: 1255454 | D19: 1095509 | E19: 987248 | F19: 853013 | G19: 619443 | H19: 439550 | I19: 294958 | J19: 184893 | K19: 127345 | L19: 89655 | M19: 70140 | N19: 91884 | O19: 131243 | R19: Total de receita de juros e ganhos (perdas) sobre instrumentos financeiros | S19: 6518820 | T19: 5733900 | U19: 5155508 | V19: 4237744 | W19: 3236590 | X19: 2409954 | Y19: 1556669 | Z19: 995963 | AA19: 698564 | AB19: 485763 | AC19: 392276 | AD19: 452564 | AE19: 586984
B21: Interchange fees | C21: 265380 | D21: 259201 | E21: 244229 | F21: 224437 | G21: 189506 | H21: 150062 | I21: 130469 | J21: 107357 | K21: 83617 | L21: 81778 | M21: 62435 | N21: 48294 | O21: 61820 | R21: Tarifas de intercâmbio | S21: 1377960 | T21: 1358990 | U21: 1278300 | V21: 1111047 | W21: 990169 | X21: 829903 | Y21: 685760 | Z21: 578300 | AA21: 458689 | AB21: 436172 | AC21: 335041 | AD21: 237867 | AE21: 276056
B22: Recharge fees | C22: 25050 | D22: 20897 | E22: 21383 | F22: 19244 | G22: 15945 | H22: 16234 | I22: 13842 | J22: 10597 | K22: 7705 | L22: 6773 | M22: 4783 | N22: 2699 | O22: 1032 | R22: Tarifas de recarga | S22: 130070 | T22: 109672 | U22: 111856 | V22: 95310 | W22: 83313 | X22: 89616 | Y22: 72859 | Z22: 57083 | AA22: 42267 | AB22: 35038 | AC22: 24936 | AD22: 13294 | AE22: 5139
B23: Rewards revenue | C23: 5547 | D23: 4651 | E23: 5433 | F23: 6022 | G23: 6332 | H23: 5854 | I23: 7122 | J23: 7276 | K23: 6605 | L23: 6041 | M23: 4313 | N23: 6624 | O23: 6546 | R23: Receita com Rewards | S23: 28802 | T23: 24568 | U23: 28621 | V23: 29625 | W23: 33085 | X23: 32904 | Y23: 37251 | Z23: 39194 | AA23: 36232 | AB23: 32609 | AC23: 24032 | AD23: 32626 | AE23: 29228
B24: Late fees | C24: 36359 | D24: 40366 | E24: 17917 | F24: 25515 | G24: 20701 | H24: 15609 | I24: 13315 | J24: 11376 | K24: 9651 | L24: 8263 | M24: 6353 | N24: 7535 | O24: 9086 | R24: Tarifas de atraso | S24: 188790 | T24: 210465 | U24: 94706 | V24: 126435 | W24: 108163 | X24: 86381 | Y24: 69904 | Z24: 61279 | AA24: 52942 | AB24: 44454 | AC24: 34958 | AD24: 37112 | AE24: 40637
B25: Other fee and commission income | C25: 30877 | D25: 29912 | E25: 30657 | F25: 29330 | G25: 25340 | H25: 19836 | I25: 21201 | J25: 14589 | K25: 10140 | L25: 10055 | M25: 8062 | N25: 5291 | O25: 6428 | R25: Outras receitas de tarifa e comissão | S25: 160326 | T25: 157115 | U25: 160619 | V25: 145110 | W25: 132400 | X25: 109916 | Y25: 111769 | Z25: 78586 | AA25: 55624 | AB25: 53502 | AC25: 42865 | AD25: 26060 | AE25: 28709
B26: Customer Program ("NuSócios") | C26: - | D26: 0 | E26: 0 | F26: 0 | G26: 0 | H26: -11180 | I26: 0 | J26: 0 | K26: 0 | L26: 0 | M26: 0 | N26: 0 | O26: 0 | R26: Programa de Clientes ("NuSócios") | S26: - | T26: 0 | U26: 0 | V26: 0 | W26: 0 | X26: -60331 | Y26: 0 | Z26: 0 | AA26: 0 | AB26: 0 | AC26: 0 | AD26: 0 | AE26: 0
B27: Total fee and commission income | C27: 363213 | D27: 355027 | E27: 319619 | F27: 304548 | G27: 257824 | H27: 196415 | I27: 185949 | J27: 151195 | K27: 117718 | L27: 112910 | M27: 85946 | N27: 70443 | O27: 84912 | R27: Total de receita de tarifas e comissões | S27: 1885948 | T27: 1860810 | U27: 1674102 | V27: 1507527 | W27: 1347130 | X27: 1088389 | Y27: 977543 | Z27: 814442 | AA27: 645754 | AB27: 601775 | AC27: 461832 | AD27: 346959 | AE27: 379769

Sheet Expenses breakdown (Abetura das
B2: Nu Holdings Ltd. | R2: Nu Holdings Ltd.
B3: Expenses Breakdown | R3: Abertura das Despesas
B4: Amounts in thousands of US$ | R4: Valores em R$ mil
B5: Back to Contents | R5: Retornar ao Índice
C10: 31/03/2023 | D10: 44926 | E10: 44834 | F10: 44742 | G10: 44651 | H10: 44561 | I10: 44469 | J10: 44377 | K10: 44286 | L10: 44196 | M10: 44104 | N10: 44012 | O10: 43921 | S10: 31/03/2023 | T10: 44926 | U10: 44834 | V10: 44742 | W10: 44651 | X10: 44561 | Y10: 44469 | Z10: 44377 | AA10: 44286 | AB10: 44196 | AC10: 44104 | AD10: 44012 | AE10: 43921
C11: US$ | D11: US$ | E11: US$ | F11: US$ | G11: US$ | H11: US$ | I11: US$ | J11: US$ | K11: US$ | L11: US$ | M11: US$ | N11: US$ | O11: US$ | S11: R$ | T11: R$ | U11: R$ | V11: R$ | W11: R$ | X11: R$ | Y11: R$ | Z11: R$ | AA11: R$ | AB11: R$ | AC11: R$ | AD11: R$ | AE11: R$
B13: Interest expense on deposits | C13: 395116 | D13: 367482 | E13: 430356 | F13: 362842 | G13: 247218 | H13: 151778 | I13: 91098 | J13: 49128 | K13: 25416 | L13: 22071 | M13: 19108 | N13: 20033 | O13: 26113 | R13: Despesa de juros sobre depósitos | S13: 2051601 | T13: 1929997 | U13: 2245499 | V13: 1805006 | W13: 1291714 | X13: 829408 | Y13: 481939 | Z13: 264638 | AA13: 139422 | AB13: 119043 | AC13: 104529 | AD13: 98670 | AE13: 116790
B14: Other interest and similar expenses | C14: 45096 | D14: 40029 | E14: 29533 | F14: 44658 | G14: 25785 | H14: 25194 | I14: 10295 | J14: 8108 | K14: 6327 | L14: 9318 | M14: 4876 | N14: 5288 | O14: 7117 | R14: Outros juros e despesas similares | S14: 234156 | T14: 209815 | U14: 155771 | V14: 222854 | W14: 134727 | X14: 137503 | Y14: 54145 | Z14: 43675 | AA14: 34707 | AB14: 49457 | AC14: 26775 | AD14: 26046 | AE14: 31831
B15: Total interest and other financial expenses | C15: 440212 | D15: 407511 | E15: 459889 | F15: 407500 | G15: 273003 | H15: 176972 | I15: 101393 | J15: 57236 | K15: 31743 | L15: 31389 | M15: 23984 | N15: 25321 | O15: 33230 | R15: Juros e outras despesas financeiras | S15: 2285757 | T15: =SUM(T13:T14) -> 2139812 | U15: 2401270 | V15: 2027860 | W15: 1426441 | X15: 966911 | Y15: 536084 | Z15: 308313 | AA15: 174129 | AB15: 168500 | AC15: 131304 | AD15: 124716 | AE15: 148621
B17: Bank slip costs | C17: 6306 | D17: 10209 | E17: 7299 | F17: 8942 | G17: 7513 | H17: 8043 | I17: 9171 | J17: 9334 | K17: 9601 | L17: 12844 | M17: 14141 | N17: 9441 | O17: 10054 | R17: Custos de boletos bancários | S17: 32743 | T17: 53459 | U17: 38443 | V17: 44272 | W17: 39255 | X17: 45161 | Y17: 47913 | Z17: 50279 | AA17: 52667 | AB17: 68937 | AC17: 75019 | AD17: 46501 | AE17: 44967
B18: Rewards expenses | C18: 12116 | D18: 10896 | E18: 10487 | F18: 10932 | G18: 10107 | H18: 10153 | I18: 10255 | J18: 8753 | K18: 7724 | L18: 8055 | M18: 6603 | N18: 8292 | O18: 6674 | R18: Despesas com Rewards | S18: 62911 | T18: 57245 | U18: 55081 | V18: 53987 | W18: 52809 | X18: 56463 | Y18: 53823 | Z18: 47150 | AA18: 42371 | AB18: 43271 | AC18: 35965 | AD18: 40841 | AE18: 29849
B19: Credit and debit card network costs | C19: 18940 | D19: 16806 | E19: 15272 | F19: 15879 | G19: 7030 | H19: 7807 | I19: 1501 | J19: 7831 | K19: 5566 | L19: 11176 | M19: 5279 | N19: 1667 | O19: 6864 | R19: Custos da rede de cartão de crédito e débito | S19: 98344 | T19: 87976 | U19: 79760 | V19: 79556 | W19: 36732 | X19: 43062 | Y19: 7295 | Z19: 42183 | AA19: 30533 | AB19: 58779 | AC19: 28205 | AD19: 8211 | AE19: 30699
B20: Other transactional expenses | C20: 15416 | D20: 11557 | E20: 11417 | F20: 12283 | G20: 9798 | H20: 6425 | I20: 7633 | J20: 3864 | K20: 3458 | L20: 7090 | M20: 5887 | N20: 3204 | O20: 9544 | R20: Outras despesas transacionais | S20: 80046 | T20: 60722 | U20: 59915 | V20: 60891 | W20: 51195 | X20: 35607 | Y20: 40324 | Z20: 20815 | AA20: 18969 | AB20: 38059 | AC20: 31970 | AD20: 15781 | AE20: 42686
B21: Total transactional expenses | C21: 52778 | D21: 49468 | E21: 44475 | F21: 48036 | G21: 34448 | H21: 32428 | I21: 28560 | J21: 29782 | K21: 26349 | L21: 39165 | M21: 31910 | N21: 22604 | O21: 33136 | R21: Total de despesas com transações | S21: 274044 | T21: =SUM(T17:T20) -> 259402 | U21: 233199 | V21: 238706 | W21: 179991 | X21: 180293 | Y21: 149355 | Z21: 160427 | AA21: 144540 | AB21: 209046 | AC21: 171159 | AD21: 111334 | AE21: 148201
B23: Customer support and operations | R23: Suporte ao cliente e operações
B24: Infrastructure and data processing costs | C24: 40167 | D24: 45786 | E24: 37521 | F24: 29462 | G24: 19394 | H24: 26533 | I24: 18779 | J24: 13822 | K24: 11794 | L24: 9419 | M24: 9800 | N24: 8842 | O24: 17664 | R24: Custos de infraestrutura e processamento de dados | S24: 208564 | T24: 239142 | U24: 195522 | V24: 146664 | W24: 101334 | X24: 145959 | Y24: 98804 | Z24: 74455 | AA24: 64697 | AB24: 51462 | AC24: 54064 | AD24: 43550 | AE24: 79002
B25: Credit analysis and collection costs | C25: 17667 | D25: 18473 | E25: 15358 | F25: 12371 | G25: 8037 | H25: 11909 | I25: 9031 | J25: 7760 | K25: 5326 | L25: 5789 | M25: 8701 | N25: 4117 | O25: 3130 | R25: Análise de crédito e custos de cobrança | S25: 91734 | T25: 96514 | U25: 80054 | V25: 61600 | W25: 41993 | X25: 65650 | Y25: 47475 | Z25: 41801 | AA25: 29216 | AB25: 31132 | AC25: 45402 | AD25: 20278 | AE25: 13999
B26: Customer services | C26: 22257 | D26: 17674 | E26: 17697 | F26: 19074 | G26: 19993 | H26: 15406 | I26: 14628 | J26: 9868 | K26: 8220 | L26: 7174 | M26: 6237 | N26: 8951 | O26: 11713 | R26: Atendimento ao cliente | S26: 115567 | T26: 93029 | U26: 93158 | V26: 93845 | W26: 104463 | X26: 85183 | Y26: 77062 | Z26: 53156 | AA26: 45092 | AB26: 39137 | AC26: 35014 | AD26: 44087 | AE26: 52386
B27: Salaries and associated benefits | C27: 17215 | D27: 16414 | E27: 11891 | F27: 11399 | G27: 8957 | H27: 5737 | I27: 5610 | J27: 4568 | K27: 3983 | L27: 3472 | M27: 3305 | N27: 3468 | O27: 3617 | R27: Salários e benefícios associados | S27: 89387 | T27: 85770 | U27: 62250 | V27: 56529 | W27: 46800 | X27: 31845 | Y27: 29469 | Z27: 24606 | AA27: 21849 | AB27: 18737 | AC27: 17937 | AD27: 17081 | AE27: 16177
B28: Credit and debit card issuance costs | C28: 4898 | D28: 2467 | E28: 4313 | F28: 2795 | G28: 3599 | H28: 5172 | I28: 2179 | J28: 4206 | K28: 2154 | L28: 2005 | M28: 367 | N28: 507 | O28: 3195 | R28: Custos de emissão de cartão de crédito e débito | S28: 25432 | T28: 13071 | U28: 22520 | V28: 13652 | W28: 18805 | X28: 28445 | Y28: 11285 | Z28: 22656 | AA28: 11816 | AB28: 10670 | AC28: 2456 | AD28: 2497 | AE28: 14290
B29: Share-based compensation | C29: - | D29: 0 | E29: 0 | F29: 0 | G29: 0 | H29: 0 | I29: 0 | J29: 0 | K29: 0 | L29: 0 | M29: 0 | N29: 0 | O29: 0 | R29: Pagamento baseado em ações | S29: - | T29: 0 | U29: 0 | V29: 0 | W29: 0 | X29: 0 | Y29: 0 | Z29: 0 | AA29: 0 | AB29: 0 | AC29: 0 | AD29: 0 | AE29: 0
B30: Specialized services expenses | C30: - | D30: 0 | E30: 0 | F30: 0 | G30: 0 | H30: 0 | I30: 0 | J30: 0 | K30: 0 | L30: 0 | M30: 0 | N30: 0 | O30: 0 | R30: Despesas com contratação de serviços especializados | S30: - | T30: 0 | U30: 0 | V30: 0 | W30: 0 | X30: 0 | Y30: 0 | Z30: 0 | AA30: 0 | AB30: 0 | AC30: 0 | AD30: 0 | AE30: 0
B31: Other personnel costs | C31: 3598 | D31: 3478 | E31: 2357 | F31: 1693 | G31: 1025 | H31: 684 | I31: 630 | J31: 513 | K31: 426 | L31: 405 | M31: 410 | N31: 485 | O31: 527 | R31: Outros custos com pessoal | S31: 18682 | T31: 18120 | U31: 12262 | V31: 8441 | W31: 5356 | X31: 3789 | Y31: 3311 | Z31: 2763 | AA31: 2337 | AB31: 2202 | AC31: 2246 | AD31: 2389 | AE31: 2357
B32: Depreciation and amortization | C32: 1978 | D32: 1510 | E32: 1074 | F32: 815 | G32: 566 | H32: 250 | I32: 703 | J32: 140 | K32: 124 | L32: 79 | M32: 0 | N32: 0 | O32: 0 | R32: Depreciação e amortização | S32: 10271 | T32: 7874 | U32: 5596 | V32: 4053 | W32: 2957 | X32: 1409 | Y32: 3736 | Z32: 754 | AA32: 680 | AB32: 408 | AC32: 0 | AD32: 0 | AE32: 0
B33: Marketing expenses | C33: - | D33: 0 | E33: 0 | F33: 0 | G33: 0 | H33: 0 | I33: 0 | J33: 0 | K33: 0 | L33: 0 | M33: 0 | N33: 0 | O33: 0 | R33: Despesa de marketing | S33: - | T33: 0 | U33: 0 | V33: 0 | W33: 0 | X33: 0 | Y33: 0 | Z33: 0 | AA33: 0 | AB33: 0 | AC33: 0 | AD33: 0 | AE33: 0
B34: Others | C34: 35 | D34: 38 | E34: 38 | F34: 94 | G34: 0 | H34: 71 | I34: 89 | J34: 91 | K34: 103 | L34: 151 | M34: 110 | N34: 57 | O34: 253 | R34: Outros | S34: 182 | T34: 199 | U34: 201 | V34: 477 | W34: 0 | X34: 401 | Y34: 464 | Z34: 491 | AA34: 565 | AB34: 812 | AC34: 609 | AD34: 281 | AE34: 1132
B35: Total | C35: 107815 | D35: =SUM(D24:D34) -> 105840 | E35: 90249 | F35: 77703 | G35: 61571 | H35: 65762 | I35: 51649 | J35: 40968 | K35: 32130 | L35: 28494 | M35: 28930 | N35: 26427 | O35: 40099 | R35: Total | S35: 559819 | T35: =SUM(T24:T34) -> 553719 | U35: 471563 | V35: 385261 | W35: 321708 | X35: 362681 | Y35: 271606 | Z35: 220682 | AA35: 176252 | AB35: 154560 | AC35: 157728 | AD35: 130163 | AE35: 179343
B37: General and administrative expenses | R37: Despesas gerais e administrativas
B38: Infrastructure and data processing costs | C38: 45949 | D38: 39091 | E38: 42167 | F38: 34496 | G38: 28587 | H38: 23004 | I38: 18599 | J38: 12708 | K38: 9522 | L38: 6490 | M38: 8112 | N38: 6597 | O38: 7912 | R38: Custos de infraestrutura e processamento de dados | S38: 238586 | T38: 205138 | U38: 220211 | V38: 170849 | W38: 149367 | X38: 126692 | Y38: 98023 | Z38: 68454 | AA38: 52234 | AB38: 35273 | AC38: 43565 | AD38: 32493 | AE38: 35386
B39: Credit analysis and collection costs | C39: 9706 | D39: 9031 | E39: 11020 | F39: 10902 | G39: 8820 | H39: 9707 | I39: 7659 | J39: 4826 | K39: 3651 | L39: 4595 | M39: 61 | N39: 3862 | O39: 3834 | R39: Análise de crédito e custos de cobrança | S39: 50397 | T39: 47588 | U39: 57740 | V39: 54026 | W39: 46085 | X39: 53392 | Y39: 40402 | Z39: 25996 | AA39: 20028 | AB39: 24329 | AC39: 1538 | AD39: 19022 | AE39: 17148
B40: Customer services | C40: 1926 | D40: 2304 | E40: 2534 | F40: 2708 | G40: 2013 | H40: 1885 | I40: 2203 | J40: 1606 | K40: 1229 | L40: 1280 | M40: 948 | N40: 1475 | O40: 1785 | R40: Atendimento ao cliente | S40: 10001 | T40: 12123 | U40: 13288 | V40: 13446 | W40: 10518 | X40: 10488 | Y40: 11600 | Z40: 8651 | AA40: 6742 | AB40: 6937 | AC40: 5341 | AD40: 7265 | AE40: 7983
B41: Salaries and associated benefits | C41: 64096 | D41: 59873 | E41: 73827 | F41: 70414 | G41: 71003 | H41: 58581 | I41: 59303 | J41: 36067 | K41: 31764 | L41: 25136 | M41: 23180 | N41: 20984 | O41: 25760 | R41: Salários e benefícios associados | S41: 332812 | T41: 315848 | U41: 387367 | V41: 346856 | W41: 370991 | X41: 324078 | Y41: 312710 | Z41: 194282 | AA41: 174245 | AB41: 135231 | AC41: 125332 | AD41: 103354 | AE41: 115212
B42: Credit and debit card issuance costs | C42: 14437 | D42: 8343 | E42: 13144 | F42: 12953 | G42: 9249 | H42: 7644 | I42: 8165 | J42: 5684 | K42: 3952 | L42: 1710 | M42: 1048 | N42: 1172 | O42: 7892 | R42: Custos de emissão de cartão de crédito e débito | S42: 74963 | T42: 44176 | U42: 68791 | V42: 64374 | W42: 48326 | X42: 42364 | Y42: 43039 | Z42: 30618 | AA42: 21679 | AB42: 9617 | AC42: 6776 | AD42: 5773 | AE42: 35297
B43: Share-based compensation | C43: 59505 | D43: 68800 | E43: 78857 | F43: 61076 | G43: 77717 | H43: 90133 | I43: 43913 | J43: 42502 | K43: 48897 | L43: 26611 | M43: 13254 | N43: 7922 | O43: 8486 | R43: Pagamento baseado em ações | S43: 308974 | T43: 362033 | U43: 413040 | V43: 298456 | W43: 406071 | X43: 494856 | Y43: 229374 | Z43: 228946 | AA43: 268229 | AB43: 139706 | AC43: 70015 | AD43: 39018 | AE43: 37954
B44: Share-based compensation - contingent share award termination (note 10b)) (i) | C44: - | D44: 355573 | E44: 0 | F44: 0 | G44: 0 | H44: 0 | I44: 0 | J44: 0 | K44: 0 | L44: 0 | M44: 0 | N44: 0 | O44: 0 | R44: Rescisão do plano de opções de ações contingentes (CSA) | S44: - | T44: 1836641 | U44: 0 | V44: 0 | W44: 0 | X44: 0 | Y44: 0 | Z44: 0 | AA44: 0 | AB44: 0 | AC44: 0 | AD44: 0 | AE44: 0
B45: Specialized services expenses | C45: 3248 | D45: 13539 | E45: 7141 | F45: 9529 | G45: 9633 | H45: 9373 | I45: 6212 | J45: 6238 | K45: 7377 | L45: 6241 | M45: 3182 | N45: 4600 | O45: 3406 | R45: Despesas com contratação de serviços especializados | S45: 16865 | T45: 70738 | U45: 37790 | V45: 46936 | W45: 50332 | X45: 51821 | Y45: 32411 | Z45: 33602 | AA45: 40467 | AB45: 33095 | AC45: 17459 | AD45: 22657 | AE45: 15233
B46: Other personnel costs | C46: 11591 | D46: 11917 | E46: 12402 | F46: 8717 | G46: 8458 | H46: 7371 | I46: 5092 | J46: 3653 | K46: 2336 | L46: 2477 | M46: 1862 | N46: 1935 | O46: 3847 | R46: Outros custos com pessoal | S46: 60185 | T46: 62460 | U46: 64687 | V46: 42989 | W46: 44193 | X46: 40469 | Y46: 26842 | Z46: 19678 | AA46: 12814 | AB46: 13385 | AC46: 10391 | AD46: 9531 | AE46: 17206
B47: Depreciation and amortization | C47: 11201 | D47: 8372 | E47: 6537 | F47: 9618 | G47: 7089 | H47: 6193 | I47: 4951 | J47: 2595 | K47: 2383 | L47: 3568 | M47: 890 | N47: 2333 | O47: 560 | R47: Depreciação e amortização | S47: 58160 | T47: 43955 | U47: 34545 | V47: 47766 | W47: 37040 | X47: 34041 | Y47: 26143 | Z47: 13978 | AA47: 13072 | AB47: 18716 | AC47: 4988 | AD47: 11491 | AE47: 2504
B48: Marketing expenses | C48: - | D48: 0 | E48: 0 | F48: 0 | G48: 0 | H48: 0 | I48: 0 | J48: 0 | K48: 0 | L48: 0 | M48: 0 | N48: 0 | O48: 0 | R48: Despesa de marketing | S48: - | T48: 0 | U48: 0 | V48: 0 | W48: 0 | X48: 0 | Y48: 0 | Z48: 0 | AA48: 0 | AB48: 0 | AC48: 0 | AD48: 0 | AE48: 0
B49: Others | C49: 15222 | D49: 20033 | E49: 14149 | F49: 9092 | G49: 22539 | H49: 10340 | I49: 10430 | J49: 6416 | K49: 4737 | L49: 3525 | M49: 4251 | N49: 6099 | O49: 7142 | R49: Outros | S49: 79038 | T49: 104877 | U49: 74505 | V49: 42796 | W49: 117766 | X49: 57149 | Y49: 55039 | Z49: 34561 | AA49: 25986 | AB49: 19565 | AC49: 23729 | AD49: 30040 | AE49: 31943
B50: Total | C50: 236881 | D50: =SUM(D38:D49) -> 596876 | E50: 261778 | F50: 229505 | G50: 245108 | H50: 224231 | I50: 166527 | J50: 122295 | K50: 115848 | L50: 81633 | M50: 56788 | N50: 56979 | O50: 70624 | R50: Total | S50: 1229981 | T50: =SUM(T38:T49) -> 3105577 | U50: 1371964 | V50: 1128494 | W50: 1280689 | X50: 1235350 | Y50: 875583 | Z50: 658766 | AA50: 635496 | AB50: 435854 | AC50: 309134 | AD50: 280644 | AE50: 315866
B52: Marketing expenses | R52: Despesas de marketing
B53: Infrastructure and data processing costs | C53: - | D53: 0 | E53: 0 | F53: 0 | G53: 0 | H53: 0 | I53: 0 | J53: 0 | K53: 0 | L53: 0 | M53: 0 | N53: 0 | O53: 0 | R53: Custos de infraestrutura e processamento de dados | S53: - | T53: 0 | U53: 0 | V53: 0 | W53: 0 | X53: 0 | Y53: 0 | Z53: 0 | AA53: 0 | AB53: 0 | AC53: 0 | AD53: 0 | AE53: 0
B54: Credit analysis and collection costs | C54: - | D54: 0 | E54: 0 | F54: 0 | G54: 0 | H54: 0 | I54: 0 | J54: 0 | K54: 0 | L54: 0 | M54: 0 | N54: 0 | O54: 0 | R54: Análise de crédito e custos de cobrança | S54: - | T54: 0 | U54: 0 | V54: 0 | W54: 0 | X54: 0 | Y54: 0 | Z54: 0 | AA54: 0 | AB54: 0 | AC54: 0 | AD54: 0 | AE54: 0
B55: Customer services | C55: - | D55: 0 | E55: 0 | F55: 0 | G55: 0 | H55: 0 | I55: 0 | J55: 0 | K55: 0 | L55: 0 | M55: 0 | N55: 0 | O55: 0 | R55: Atendimento ao cliente | S55: - | T55: 0 | U55: 0 | V55: 0 | W55: 0 | X55: 0 | Y55: 0 | Z55: 0 | AA55: 0 | AB55: 0 | AC55: 0 | AD55: 0 | AE55: 0
B56: Salaries and associated benefits | C56: 5272 | D56: 4428 | E56: 4063 | F56: 3781 | G56: 3158 | H56: 2955 | I56: 2317 | J56: 1431 | K56: 819 | L56: 938 | M56: 938 | N56: 361 | O56: 570 | R56: Salários e benefícios associados | S56: 27374 | T56: 23209 | U56: 21269 | V56: 18722 | W56: 16501 | X56: 14509 | Y56: 12222 | Z56: 7708 | AA56: 4493 | AB56: 4988 | AC56: 4918 | AD56: 1778 | AE56: 2549
B57: Credit and debit card issuance costs | C57: - | D57: 0 | E57: 0 | F57: 0 | G57: 0 | H57: 0 | I57: 0 | J57: 0 | K57: 0 | L57: 0 | M57: 0 | N57: 0 | O57: 0 | R57: Custos de emissão de cartão de crédito e débito | S57: - | T57: 0 | U57: 0 | V57: 0 | W57: 0 | X57: 0 | Y57: 0 | Z57: 0 | AA57: 0 | AB57: 0 | AC57: 0 | AD57: 0 | AE57: 0
B58: Share-based compensation | C58: - | D58: 0 | E58: 0 | F58: 0 | G58: 0 | H58: 0 | I58: 0 | J58: 0 | K58: 0 | L58: 0 | M58: 0 | N58: 0 | O58: 0 | R58: Pagamento baseado em ações | S58: - | T58: 0 | U58: 0 | V58: 0 | W58: 0 | X58: 0 | Y58: 0 | Z58: 0 | AA58: 0 | AB58: 0 | AC58: 0 | AD58: 0 | AE58: 0
B59: Specialized services expenses | C59: - | D59: 0 | E59: 0 | F59: 0 | G59: 0 | H59: 0 | I59: 0 | J59: 0 | K59: 0 | L59: 0 | M59: 0 | N59: 0 | O59: 0 | R59: Despesas com contratação de serviços especializados | S59: - | T59: 0 | U59: 0 | V59: 0 | W59: 0 | X59: 0 | Y59: 0 | Z59: 0 | AA59: 0 | AB59: 0 | AC59: 0 | AD59: 0 | AE59: 0
B60: Other personnel costs | C60: 500 | D60: 450 | E60: 442 | F60: 254 | G60: 279 | H60: -230 | I60: 76 | J60: 53 | K60: 378 | L60: 47 | M60: 47 | N60: 15 | O60: 31 | R60: Outros custos com pessoal | S60: 2596 | T60: 2354 | U60: 2300 | V60: 1248 | W60: 1458 | X60: 514 | Y60: 399 | Z60: 286 | AA60: 2073 | AB60: 250 | AC60: 246 | AD60: 74 | AE60: 139
B61: Depreciation and amortization | C61: - | D61: 0 | E61: 0 | F61: 0 | G61: 0 | H61: 0 | I61: 0 | J61: 0 | K61: 0 | L61: 0 | M61: 0 | N61: 0 | O61: 0 | R61: Depreciação e amortização | S61: - | T61: 0 | U61: 0 | V61: 0 | W61: 0 | X61: 0 | Y61: 0 | Z61: 0 | AA61: 0 | AB61: 0 | AC61: 0 | AD61: 0 | AE61: 0
B62: Marketing expenses | C62: 13500 | D62: 46200 | E62: 33598 | F62: 32173 | G62: 24171 | H62: 31783 | I62: 23175 | J62: 13147 | K62: 3670 | L62: 6915 | M62: 3103 | N62: 969 | O62: 5492 | R62: Despesa de marketing | S62: 70098 | T62: 241389 | U62: 175818 | V62: 159714 | W62: 126293 | X62: 174013 | Y62: 122718 | Z62: 70819 | AA62: 20132 | AB62: 36448 | AC62: 16811 | AD62: 4773 | AE62: 24563
B63: Others | C63: - | D63: 0 | E63: 0 | F63: 0 | G63: 0 | H63: 0 | I63: 0 | J63: 0 | K63: 0 | L63: 0 | M63: 0 | N63: 0 | O63: 0 | R63: Outros | S63: - | T63: 0 | U63: 0 | V63: 0 | W63: 0 | X63: 0 | Y63: 0 | Z63: 0 | AA63: 0 | AB63: 0 | AC63: 0 | AD63: 0 | AE63: 0
B64: Total | C64: 19272 | D64: =SUM(D53:D63) -> 51078 | E64: 38103 | F64: 36208 | G64: 27608 | H64: 34508 | I64: 25568 | J64: 14631 | K64: 4867 | L64: 7900 | M64: 4088 | N64: 1345 | O64: 6093 | R64: Total | S64: 100068 | T64: =SUM(T53:T63) -> 266952 | U64: 199387 | V64: 179684 | W64: 144252 | X64: 189036 | Y64: 135339 | Z64: 78813 | AA64: 26698 | AB64: 41686 | AC64: 21975 | AD64: 6625 | AE64: 27251
B66: Other income/expenses | R66: Outras receitas/ despesas
B67: Infrastructure and data processing costs | C67: - | D67: 0 | E67: 0 | F67: 0 | G67: 0 | H67: 0 | I67: 0 | J67: 0 | K67: 0 | L67: 0 | M67: 0 | N67: 0 | O67: 0 | R67: Custos de infraestrutura e processamento de dados | S67: - | T67: 0 | U67: 0 | V67: 0 | W67: 0 | X67: 0 | Y67: 0 | Z67: 0 | AA67: 0 | AB67: 0 | AC67: 0 | AD67: 0 | AE67: 0
B68: Credit analysis and collection costs | C68: - | D68: 0 | E68: 0 | F68: 0 | G68: 0 | H68: 0 | I68: 0 | J68: 0 | K68: 0 | L68: 0 | M68: 0 | N68: 0 | O68: 0 | R68: Análise de crédito e custos de cobrança | S68: - | T68: 0 | U68: 0 | V68: 0 | W68: 0 | X68: 0 | Y68: 0 | Z68: 0 | AA68: 0 | AB68: 0 | AC68: 0 | AD68: 0 | AE68: 0
B69: Customer services | C69: - | D69: 0 | E69: 0 | F69: 0 | G69: 0 | H69: 0 | I69: 0 | J69: 0 | K69: 0 | L69: 0 | M69: 0 | N69: 0 | O69: 0 | R69: Atendimento ao cliente | S69: - | T69: 0 | U69: 0 | V69: 0 | W69: 0 | X69: 0 | Y69: 0 | Z69: 0 | AA69: 0 | AB69: 0 | AC69: 0 | AD69: 0 | AE69: 0
B70: Salaries and associated benefits | C70: - | D70: 0 | E70: 0 | F70: 0 | G70: 0 | H70: 0 | I70: 0 | J70: 0 | K70: 0 | L70: 0 | M70: 0 | N70: 0 | O70: 0 | R70: Salários e benefícios associados | S70: - | T70: 0 | U70: 0 | V70: 0 | W70: 0 | X70: 0 | Y70: 0 | Z70: 0 | AA70: 0 | AB70: 0 | AC70: 0 | AD70: 0 | AE70: 0
B71: Credit and debit card issuance costs | C71: - | D71: 0 | E71: 0 | F71: 0 | G71: 0 | H71: 0 | I71: 0 | J71: 0 | K71: 0 | L71: 0 | M71: 0 | N71: 0 | O71: 0 | R71: Custos de emissão de cartão de crédito e débito | S71: - | T71: 0 | U71: 0 | V71: 0 | W71: 0 | X71: 0 | Y71: 0 | Z71: 0 | AA71: 0 | AB71: 0 | AC71: 0 | AD71: 0 | AE71: 0
B72: Share-based compensation | C72: - | D72: 0 | E72: 0 | F72: 0 | G72: 0 | H72: 0 | I72: 0 | J72: 0 | K72: 0 | L72: 0 | M72: 0 | N72: 0 | O72: 0 | R72: Pagamento baseado em ações | S72: - | T72: 0 | U72: 0 | V72: 0 | W72: 0 | X72: 0 | Y72: 0 | Z72: 0 | AA72: 0 | AB72: 0 | AC72: 0 | AD72: 0 | AE72: 0
B73: Specialized services expenses | C73: - | D73: 0 | E73: 0 | F73: 0 | G73: 0 | H73: 0 | I73: 0 | J73: 0 | K73: 0 | L73: 0 | M73: 0 | N73: 0 | O73: 0 | R73: Despesas com contratação de serviços especializados | S73: - | T73: 0 | U73: 0 | V73: 0 | W73: 0 | X73: 0 | Y73: 0 | Z73: 0 | AA73: 0 | AB73: 0 | AC73: 0 | AD73: 0 | AE73: 0
B74: Other personnel costs | C74: - | D74: 0 | E74: 0 | F74: 0 | G74: 0 | H74: 0 | I74: 0 | J74: 0 | K74: 0 | L74: 0 | M74: 0 | N74: 0 | O74: 0 | R74: Outros custos com pessoal | S74: - | T74: 0 | U74: 0 | V74: 0 | W74: 0 | X74: 0 | Y74: 0 | Z74: 0 | AA74: 0 | AB74: 0 | AC74: 0 | AD74: 0 | AE74: 0
B75: Depreciation and amortization | C75: - | D75: 0 | E75: 0 | F75: 0 | G75: 0 | H75: 0 | I75: 0 | J75: 0 | K75: 0 | L75: 0 | M75: 0 | N75: 0 | O75: 0 | R75: Depreciação e amortização | S75: - | T75: 0 | U75: 0 | V75: 0 | W75: 0 | X75: 0 | Y75: 0 | Z75: 0 | AA75: 0 | AB75: 0 | AC75: 0 | AD75: 0 | AE75: 0
B76: Marketing expenses | C76: - | D76: 0 | E76: 0 | F76: 0 | G76: 0 | H76: 0 | I76: 0 | J76: 0 | K76: 0 | L76: 0 | M76: 0 | N76: 0 | O76: 0 | R76: Despesa de marketing | S76: - | T76: 0 | U76: 0 | V76: 0 | W76: 0 | X76: 0 | Y76: 0 | Z76: 0 | AA76: 0 | AB76: 0 | AC76: 0 | AD76: 0 | AE76: 0
B77: Others | C77: 43285 | D77: 46285 | E77: 31792 | F77: 44729 | G77: 27458 | H77: -9110 | I77: 1962 | J77: -4954 | K77: 16199 | L77: -15911 | M77: 2106 | N77: 5692 | O77: 17648 | R77: Outros | S77: 224753 | T77: 242258 | U77: 167473 | V77: 222960 | W77: 143468 | X77: -48333 | Y77: 9869 | Z77: -26686 | AA77: 88861 | AB77: -80165 | AC77: 14435 | AD77: 28035 | AE77: 78931
B78: Total | C78: 43285 | D78: 46285 | E78: 31792 | F78: 44729 | G78: 27458 | H78: -9110 | I78: 1962 | J78: -4954 | K78: 16199 | L78: -15911 | M78: 2106 | N78: 5692 | O78: 17648 | R78: Total | S78: 224753 | T78: =T77 -> 242258 | U78: 167473 | V78: 222960 | W78: 143468 | X78: -48333 | Y78: 9869 | Z78: -26686 | AA78: 88861 | AB78: -80165 | AC78: 14435 | AD78: 28035 | AE78: 78931

Sheet Credit operations (Operações de
B2: Nu Holdings Ltd. | P2: Nu Holdings Ltd.
B3: Credit Operations | P3: Operações de Crédito
B4: Amounts in thousands of US$ | P4: Valores em R$ mil
B5: Back to Contents | P5: Retornar ao Índice
C10: 31/03/2023 | D10: 44926 | E10: 44834 | F10: 44742 | G10: 44651 | H10: 44561 | I10: 44469 | J10: 44377 | K10: 44286 | L10: 44196 | M10: 44012 | Q10: 31/03/2023 | R10: 44926 | S10: 44834 | T10: 44742 | U10: 44651 | V10: 44561 | W10: 44469 | X10: 44377 | Y10: 44286 | Z10: 44196 | AA10: 44012
B11: Credit card receivables | C11: US$ | D11: US$ | E11: US$ | F11: US$ | G11: US$ | H11: US$ | I11: US$ | J11: US$ | K11: US$ | L11: US$ | M11: US$ | P11: Recebíveis de cartão de crédito | Q11: R$ | R11: R$ | S11: R$ | T11: R$ | U11: R$ | V11: R$ | W11: R$ | X11: R$ | Y11: R$ | Z11: R$ | AA11: R$
B13: Receivables - current | C13: 4666175 | D13: 4236235 | E13: 3509311 | F13: 3228581 | G13: 3028412 | H13: 2341492 | I13: 2052437 | J13: 1919929 | K13: 1406056 | L13: 1475417 | M13: 974804 | P13: Recebíveis - corrente | Q13: 23625311 | R13: 22369015 | S13: 19004673 | T13: 16972003 | U13: 14359821 | V13: 13055690 | W13: 11171209 | X13: 9541279 | Y13: 7921298 | Z13: 7669955 | AA13: 5329838
B14: Receivables - installments | C14: 4882951 | D14: 4259979 | E14: 3598374 | F14: 3363952 | G14: 3306245 | H14: 2483647 | I14: 2045231 | J14: 1933849 | K14: 1394859 | L14: 1443793 | M14: 927329 | P14: Recebíveis - parcelados | Q14: 24722869 | R14: 22494393 | S14: 19486994 | T14: 17683623 | U14: 15677222 | V14: 13848319 | W14: 11131988 | X14: 9610456 | Y14: 7858217 | Z14: 7505558 | AA14: 5070264
B15: Receivables - revolving | C15: 905471 | D15: 770011 | E15: 691915 | F15: 570668 | G15: 468577 | H15: 337014 | I15: 270206 | J15: 233646 | K15: 193776 | L15: 199662 | M15: 323668 | P15: Recebíveis - rotativo | Q15: 4584490 | R15: 4065966 | S15: 3747066 | T15: 2999888 | U15: 2221852 | V15: 1879123 | W15: 1470704 | X15: 1161127 | Y15: 1091676 | Z15: 1037943 | AA15: 1769687
B16: Total receivables | C16: 10454597 | D16: 9266225 | E16: 7799600 | F16: 7163201 | G16: 6803234 | H16: 5162153 | I16: 4367874 | J16: 4087424 | K16: 2994691 | L16: 3118872 | M16: 2225801 | P16: Total dos recebíveis | Q16: 52932670 | R16: 48929374 | S16: 42238733 | T16: 37655514 | U16: 32258895 | V16: 28783132 | W16: 23773901 | X16: 20312862 | Y16: 16871191 | Z16: 16213456 | AA16: 12169789
B17: Fair value adjustment - portfolio hedge | C17: -18 | D17: -51 | E17: -61 | F17: -212 | G17: -70 | H17: 0 | I17: 0 | J17: 0 | K17: 0 | L17: 0 | M17: 0 | P17: Ajuste a valor de mercado - hedge de portfólio | Q17: -91 | R17: -269 | S17: -330 | T17: -1114 | U17: -332 | V17: 0 | W17: 0 | X17: 0 | Y17: 0 | Z17: 0 | AA17: 0
B18: Total | C18: 10454579 | D18: 9266174 | E18: 7799539 | F18: 7162989 | G18: 6803164 | H18: 5162153 | I18: 4367874 | J18: 4087424 | K18: 2994691 | L18: 3118872 | M18: 2225801 | P18: Total | Q18: 52932579 | R18: 48929105 | S18: 42238403 | T18: 37654400 | U18: 32258563 | V18: 28783132 | W18: 23773901 | X18: 20312862 | Y18: 16871191 | Z18: 16213456 | AA18: 12169789
B20: Credit card ECL allowance | P20: Provisão para perdas de crédito esperadas de cartões de crédito
B21: Presented as deduction of receivables | C21: -1296127 | D21: -1033102 | E21: -811591 | F21: -684519 | G21: -568340 | H21: -381633 | I21: -306369 | J21: -267533 | K21: -206878 | L21: -209965 | M21: -182189 | P21: Apresentada como dedução dos recebíveis | Q21: -6562421 | R21: -5455192 | S21: -4395171 | T21: -3598379 | U21: -2694898 | V21: -2127909 | W21: -1667536 | X21: -1329532 | Y21: -1165491 | Z21: -1091503 | AA21: -996137
B22: Presented as "Other liabilities" | C22: -19901 | D22: -17566 | E22: -12734 | F22: -12828 | G22: -12150 | H22: -9046 | I22: -7954 | J22: -7494 | K22: -8564 | L22: -7577 | M22: 0 | P22: Apresentada como "Outros passivos" | Q22: -100761 | R22: -92756 | S22: -68961 | T22: -67434 | U22: -57612 | V22: -50439 | W22: -43293 | X22: -37242 | Y22: -48245 | Z22: -39389 | AA22: 0
B23: Total credit card ECL allowance | C23: -1316028 | D23: -1050668 | E23: -824325 | F23: -697347 | G23: -580490 | H23: -390679 | I23: -314323 | J23: -275027 | K23: -215442 | L23: -217542 | M23: -182189 | P23: Total da provisão para perdas de crédito esperadas de cartões de crédito | Q23: -6663182 | R23: -5547948 | S23: -4464132 | T23: -3665813 | U23: -2752510 | V23: -2178348 | W23: -1710829 | X23: -1366774 | Y23: -1213736 | Z23: -1130892 | AA23: -996137
B24: Receivables, net | C24: 9138551 | D24: 8215506 | E24: 6975214 | F24: 6465642 | G24: 6222674 | H24: 4771474 | I24: 4053551 | J24: 3812397 | K24: 2779249 | L24: 2901330 | M24: 2043612 | P24: Valor líquido dos recebíveis | Q24: 46269397 | R24: 43381157 | S24: 37774271 | T24: 33988587 | U24: 29506053 | V24: 26604784 | W24: 22063072 | X24: 18946088 | Y24: 15657455 | Z24: 15082564 | AA24: 11173652
B25: Total receivables presented as assets | C25: 9158452 | D25: 8233072 | E25: 6987948 | F25: 6478470 | G25: 6234824 | H25: 4780520 | I25: 4061505 | J25: 3819891 | K25: 2787813 | L25: 2908907 | M25: 2043612 | P25: Total dos recebíveis apresentados como ativo | Q25: 46370158 | R25: 43473913 | S25: 37843232 | T25: 34056021 | U25: 29563665 | V25: 26655223 | W25: 22106366 | X25: 18983330 | Y25: 15705700 | Z25: 15121953 | AA25: 11173652
C27: 31/03/2023 | D27: 44926 | E27: 44834 | F27: 44742 | G27: 44651 | H27: 44561 | I27: 44469 | J27: 44377 | K27: 44286 | L27: 44196 | M27: 44012 | R27: 44926 | S27: 44834 | T27: 44742 | U27: 44651 | V27: 44561 | W27: 44469 | X27: 44377 | Y27: 44286 | Z27: 44196 | AA27: 44012
B28: Lending receivables | C28: US$ | D28: US$ | E28: US$ | F28: US$ | G28: US$ | H28: US$ | I28: US$ | J28: US$ | K28: US$ | L28: US$ | M28: US$ | P28: Recebíves de empréstimos pessoais | R28: R$ | S28: R$ | T28: R$ | U28: R$ | V28: R$ | W28: R$ | X28: R$ | Y28: R$ | Z28: R$ | AA28: R$
B30: Lending to individuals | C30: 2337419 | D30: 1976499 | E30: 1907405 | F30: 1952511 | G30: 2009494 | H30: 1392350 | I30: 903061 | J30: 592454 | K30: 303897 | L30: 200904 | M30: 60848 | P30: Empréstimos a pessoas físicas | Q30: 11834586 | R30: 10436706 | S30: 10329551 | T30: 10263959 | U30: 9528417 | V30: 7763465 | W30: 4915271 | X30: 2944260 | Y30: 1712064 | Z30: 1044400 | AA30: 332693
B31: Loan ECL allowance | C31: -315911 | D31: -300223 | E31: -301630 | F31: -270277 | G31: -340517 | H31: -197536 | I31: -110325 | J31: -72768 | K31: -39355 | L31: -26210 | M31: -11672 | P31: ECL - empréstimos | Q31: -1599489 | R31: -1585298 | S31: -1633477 | T31: -1420792 | U31: -1614629 | V31: -1101421 | W31: -600488 | X31: -361628 | Y31: -221714 | Z31: -136253 | AA31: -63818
B32: Total receivables | C32: 2021508 | D32: 1676276 | E32: 1605775 | F32: 1682234 | G32: 1668977 | H32: 1194814 | I32: 792736 | J32: 519686 | K32: 264542 | L32: 174694 | M32: 49176 | P32: Total de recebíveis | Q32: 10235097 | R32: 8851408 | S32: 8696074 | T32: 8843167 | U32: 7913788 | V32: 6662044 | W32: 4314783 | X32: 2582632 | Y32: 1490350 | Z32: 908147 | AA32: 268875
B33: Fair value adjustment - portfolio hedge | C33: -1317 | D33: -2836 | E33: -2670 | F33: -6458 | G33: -1460 | H33: - | I33: 0 | J33: 0 | K33: 0 | L33: 0 | M33: 0 | P33: Ajuste a valor de mercado - hedge de portfólio | Q33: -6668 | R33: -14975 | S33: -14459 | T33: -33948 | U33: -6923 | V33: - | W33: 0 | X33: 0 | Y33: 0 | Z33: 0 | AA33: 0
B34: Total | C34: 2020191 | D34: 1673440 | E34: 1603105 | F34: 1675776 | G34: 1667517 | H34: 1194814 | I34: 792736 | J34: 519686 | K34: 264542 | L34: 174694 | M34: 49176 | P34: Total | Q34: 10228429 | R34: 8836433 | S34: 8681615 | T34: 8809219 | U34: 7906865 | V34: 6662044 | W34: 4314783 | X34: 2582632 | Y34: 1490350 | Z34: 908147 | AA34: 268875
C36: 31/03/2023 | D36: 44926 | E36: 44834 | F36: 44742 | G36: 44651 | H36: 44561 | I36: 44469 | J36: 44377 | K36: 44286 | L36: 44196 | M36: 44012 | Q36: 31/03/2023 | R36: 44926 | S36: 44834 | T36: 44742 | U36: 44651 | V36: 44561 | W36: 44469 | X36: 44377 | Y36: 44286 | Z36: 44196 | AA36: 44012
B37: Other receivables | C37: US$ | D37: US$ | E37: US$ | F37: US$ | G37: US$ | H37: US$ | I37: US$ | J37: US$ | K37: US$ | L37: US$ | M37: US$ | P37: Outros recebíveis | Q37: R$ | R37: R$ | S37: R$ | T37: R$ | U37: R$ | V37: R$ | W37: R$ | X37: R$ | Y37: R$ | Z37: R$ | AA37: R$
B39: Other receivables | C39: 1078801 | D39: 521670 | E39: 381782 | F39: 374188 | G39: 285632 | H39: 50349 | I39: 0 | J39: 0 | K39: 0 | L39: 0 | M39: 0 | P39: Outros recebíveis | Q39: 5462077 | R39: 2754626 | S39: 2067540 | T39: 1967031 | U39: 1354380 | V39: 280737 | W39: 0 | X39: 0 | Y39: 0 | Z39: 0 | AA39: 0
B40: Total | C40: =C39 -> 1078801 | D40: 521670 | E40: 381782 | F40: 374188 | G40: 285632 | H40: 50349 | I40: 0 | J40: 0 | K40: 0 | L40: 0 | M40: 0 | P40: Total | Q40: =Q39 -> 5462077 | R40: 2754626 | S40: 2067540 | T40: 1967031 | U40: 1354380 | V40: 280737 | W40: 0 | X40: 0 | Y40: 0 | Z40: 0 | AA40: 0

Sheet Write-offs and Rec (Baixas e Re
B2: Nu Holdings Ltd. | H2: Nu Holdings Ltd.
B3: Write-offs and Recoveries | H3: Baixas e Recuperação das Carteiras
B4: Amounts in thousands of US$ | H4: Valores em US$ mil
B5: Back to Contents | H5: Retornar ao Índice
D10: 31/03/2023 | E10: 44926 | F10: 44834 | G10: 44742 | H10: 44651 | I10: 44561 | J10: 44469 | K10: 44377 | L10: 44286 | M10: 44196 | N10: 44012
D11: US$ | E11: US$ | F11: US$ | G11: US$ | H11: US$ | I11: US$ | J11: US$ | K11: US$ | L11: US$ | M11: US$ | N11: US$
B13: Credit card portfolio | C13: Carteira de cartão de crédito | D13: -174938 | E13: -290974 | F13: -182333 | G13: -100089 | H13: -50608 | I13: -118518 | J13: -94346 | K13: -71767 | L13: -43248 | M13: -116856 | N13: -58099
B14: Lending portfolio | C14: Carteira de empréstimos pessoais | D14: -106614 | E14: -408605 | F14: -282374 | G14: -169452 | H14: -11696 | I14: -13223 | J14: -9276 | K14: -7030 | L14: -3614 | M14: -4525 | N14: -293
B15: Total write-offs | C15: Total de baixas | D15: -281552 | E15: =SUM(E13:E14) -> -699579 | F15: =SUM(F13:F14) -> -464707 | G15: =SUM(G13:G14) -> -269541 | H15: =SUM(H13:H14) -> -62304 | I15: =SUM(I13:I14) -> -131741 | J15: =SUM(J13:J14) -> -103622 | K15: =SUM(K13:K14) -> -78797 | L15: =SUM(L13:L14) -> -46862 | ... N15: =SUM(N13:N14) -> -58392
B17: Credit card portfolio | C17: Carteira de cartão de crédito | D17: 13386 | E17: 31491 | F17: 18270 | G17: 9754 | H17: 3545 | I17: 22494 | J17: 18079 | K17: 5811 | L17: 5868 | M17: 18202 | N17: 6558
B18: Lending portfolio | C18: Carteira de empréstimos pessoais | D18: 3756 | E18: 4520 | F18: 1869 | G18: 1217 | H18: 222 | I18: 542 | J18: 358 | K18: 126 | L18: 48 | M18: 103 | N18: 58
B19: Total Recoveries | C19: Total de recuperações | D19: 17142 | E19: =SUM(E17:E18) -> 36011 | F19: =SUM(F17:F18) -> 20139 | G19: =SUM(G17:G18) -> 10971 | H19: =SUM(H17:H18) -> 3767 | I19: =SUM(I17:I18) -> 23036 | J19: =SUM(J17:J18) -> 18437 | K19: =SUM(K17:K18) -> 5937 | L19: =SUM(L17:L18) -> 5916 | ... N19: =SUM(N17:N18) -> 6616
B21: The information included in this spreadsheet is acumulated as of date.
B22: As informações incluídas nesta planilha é acumulado para a data base.

Sheet NPLs (Inadimplência)
B2: Nu Holdings Ltd. | H2: Nu Holdings Ltd.
B3: Non-Performing Loans (NPLs) | H3: Inadimplência
B4: % | H4: %
B5: Back to Contents | H5: Retornar ao Índice
D10: 45016 | E10: 44926 | F10: 44834 | G10: 44742 | H10: 44651 | I10: 44561 | J10: 44469 | K10: 44377 | L10: 44286 | M10: 44196 | N10: 44104 | O10: 44012 | P10: 43921
B11: Consumer Finance Portfolio | C11: Carteira Crédito ao Consumidor
B13: 15-90 days NPL | C13: 15 a 90 dias | D13: 0.044 | E13: 0.037 | F13: 0.042 | G13: 0.037 | H13: 0.037 | I13: 0.026 | J13: 0.023 | K13: 0.022 | L13: 0.024 | M13: 0.013 | N13: 0.012 | O13: 0.022 | P13: 0.034
B14: 90+ NPL | C14: 90+dias | D14: 0.055 | E14: 0.052 | F14: 0.047 | G14: 0.041 | H14: 0.035 | I14: 0.031 | J14: 0.032 | K14: 0.03 | L14: 0.03 | M14: 0.037 | N14: 0.052 | O14: 0.062 | P14: 0.05
B16: Consumer Finance Portfolio (Constant product mix Q4'19) | C16: Carteira Crédito ao Consumidor (Mix constante de produtos desde 4T19)
B18: 15-90 days NPL | C18: 15 a 90 dias | D18: 0.039 | E18: 0.031 | F18: 0.034 | G18: 0.029 | H18: 0.03 | I18: 0.022 | J18: 0.021 | K18: 0.021 | L18: 0.024 | M18: 0.012 | N18: 0.012 | O18: 0.022 | P18: 0.034
B19: 90+ NPL | C19: 90+dias | D19: 0.06 | E19: 0.056 | F19: 0.051 | G19: 0.044 | H19: 0.039 | I19: 0.036 | J19: 0.036 | K19: 0.032 | L19: 0.031 | M19: 0.039 | N19: 0.053 | O19: 0.062 | P19: 0.05
B21: Includes information of Brazilian operation only
B22: Inclui informações da operação brasileira apenas

Sheet Operating figures (Informações 
B2: Nu Holdings Ltd. | G2: Nu Holdings Ltd.
B3: Operating Figures | G3: Informações Operacionais
B4: Amounts in billion of US$, unless otherwise noted | G4: Valores em US$ bilhões, exceto se mencionado de outra forma
B5: Back to Contents | G5: Retornar ao Índice
C10: 45016 | D10: 44926 | E10: 44834 | F10: 44742 | G10: 44651 | H10: 44561 | I10: 44469 | J10: 44377 | K10: 44286 | L10: 44196 | M10: 44104 | N10: 44012 | O10: 43921
B11: Number of customers (# MM)
B13: Brazil | Brasil | C13: 75.3 | D13: 70.9 | E13: 66.9 | F13: 62.3 | G13: 57.3 | H13: 52.4 | I13: 47.3 | J13: 41.3 | K13: 36.9 | L13: 33.2 | M13: 29.7 | N13: 26.1 | O13: 23.5
B14: México | C14: 3.2 | D14: 3.2 | E14: 3 | F14: 2.7 | G14: 2.1 | H14: 1.4 | I14: 0.7 | J14: 0.4 | K14: 0.2 | L14: 0.1 | M14: 0 | N14: 0 | O14: 0
B15: Colômbia | C15: 0.6 | D15: 0.6 | E15: 0.4 | F15: 0.3 | G15: 0.2 | H15: 0.1 | I15: 0 | J15: 0 | K15: 0 | L15: 0 | M15: 0 | N15: 0 | O15: 0
B17: Number of active customers | Quantidade de clientes ativos (# MM)
B19: Brazil | Brasil | C19: 61.7 | D19: 58.1 | E19: 54.5 | F19: 49.8 | G19: 44.6 | H19: 39.9 | I19: 34.6 | J19: 29.6 | K19: 25.4 | L19: 21.7 | M19: 18.6 | N19: 15.7 | O19: 14
B20: NuAccount | NuConta | C20: 55.8 | D20: 52.5 | E20: 49.2 | F20: 44.6 | G20: 39.5 | H20: 34.7 | I20: 29.3 | J20: 24.3 | K20: 19.6 | L20: 16.3 | M20: 12.9 | N20: 9.4 | O20: 7.1
B21: Credit Card | Cartão de crédito | C21: 31.5 | D21: 30.4 | E21: 28.9 | F21: 26.7 | G21: 25 | H21: 23.3 | I21: 20.9 | J21: 18.2 | K21: 16.3 | L21: 14.2 | M21: 11.7 | N21: 10.3 | O21: 9.9
B22: Personal Loans | Empréstimos pessoais | C22: 6.1 | D22: 5.2 | E22: 5.3 | F22: 4.2 | G22: 2.7 | H22: 2.3 | I22: 1.4 | J22: 0.9 | K22: 0.5 | L22: 0.3 | M22: 0.1 | N22: 0.1 | O22: 0.1
B23: Life Insurance policies | Contratos de seguro de vida | C23: 1 | D23: 1 | E23: 0.8 | F23: 0.7 | G23: 0.6 | H23: 0.5 | I23: 0.4 | J23: 0.3 | K23: 0.2 | L23: 0 | M23: 0 | N23: 0 | O23: 0
B24: NuInvest customers | Clientes da NuInvest | C24: 9.2 | D24: 7.4 | E24: 6.2 | F24: 4.7 | G24: 4 | H24: 3.5 | I24: 2.5 | J24: 2 | K24: 1.6 | L24: 0 | M24: 0 | N24: 0 | O24: 0
B25: NuCripto | C25: 1.4 | D25: 1.3 | E25: 1.3 | F25: 0.5 | G25: 0 | H25: 0 | I25: 0 | J25: 0 | K25: 0 | L25: 0 | M25: 0 | N25: 0 | O25: 0
B26: SME Accounts | Contas PJ | C26: 1.6 | D26: 1.4 | E26: 1.3 | F26: 1.1 | G26: 0.9 | H26: 0.8 | I26: 0.6 | J26: 0.4 | K26: 0.3 | L26: 0 | M26: 0 | N26: 0 | O26: 0
B28: Payment volume | Volume de pagamentos (US$ Bn)
B30: Total PV | C30: 23.3 | D30: 23.8 | E30: 21.2 | F30: 20 | G30: 15.9 | H30: 14.4 | I30: 12.1 | J30: 9.9 | K30: 7.5 | L30: 7.6 | M30: 5.7 | N30: 4.1 | O30: 5.1
B31: Credit Card | Cartão de Credito | C31: 15.1 | D31: 15.2 | E31: 13.6 | F31: 13.1 | G31: 10.6 | H31: 9.6 | I31: 8.4 | J31: 7.2 | K31: 5.6 | L31: 5.8 | M31: 4.6 | N31: 3.6 | O31: 4.6
B32: Prepaid Card | Cartão Pré-pago | C32: 8.2 | D32: 8.7 | E32: 7.6 | F32: 7 | G32: 5.3 | H32: 4.8 | I32: 3.7 | J32: 2.7 | K32: 1.8 | L32: 1.8 | M32: 1.1 | N32: 0.5 | O32: 0.5
B34: Number of employees | Quantidade de colaboradores (# '000)
B36: Total | C36: 7.8 | D36: 8 | E36: 8 | F36: 7.7 | G36: 6.9 | H36: 6.1 | I36: 5.4 | J36: 4.5 | K36: 3.3 | L36: 2.9 | M36: 2.7 | N36: 2.7 | O36: 2.6

Sheet Managerial indicators (Indicado
B2: Nu Holdings Ltd. | G2: Nu Holdings Ltd.
B3: Managerial Indicators | G3: Indicadores Gerenciais
B4: Amounts in billion of US$, unless otherwise noted | G4: Valores em US$ bilhões, exceto se mencionado de outra forma
B5: Back to Contents | G5: Retornar ao Índice
C10: 45016 | D10: 44926 | E10: 44834 | F10: 44742 | G10: 44651 | H10: 44561 | I10: 44469 | J10: 44377 | K10: 44286 | L10: 44196 | M10: 44104 | N10: 44012 | O10: 43921
C11: US$ | D11: US$ | E11: US$ | F11: US$ | G11: US$ | H11: US$ | I11: US$ | J11: US$ | K11: US$ | L11: US$ | M11: US$ | N11: US$ | O11: US$
B12: Average Revenue per Active Customer (ARPAC) | Receita Média por Cliente Ativo - US$ | C12: 8.6 | D12: 8.2 | E12: 7.9 | F12: 7.8 | G12: 6.7 | H12: 5.6 | I12: 4.9 | J12: 4 | K12: 3.5 | L12: 3.3 | M12: 3 | N12: 3.6 | O12: 5.5
B14: Cost to Serve per Active Customer | Custo de Serviço por Cliente Ativo - US$ | C14: 0.8 | D14: 0.9 | E14: 0.8 | F14: 0.8 | G14: 0.7 | H14: 0.9 | I14: 0.8 | J14: 0.9 | K14: 0.8 | L14: 1.1 | M14: 1.2 | N14: 1.1 | O14: 1.9
B16: Interest Earning Portfolio (IEP) | Portfólio Sujeito a Ganho de Juros (IEP) | C16: 5.2 | D16: 4 | E16: 3.5 | F16: 3.2 | G16: 3.1 | H16: 2 | I16: 1.4 | J16: 1 | K16: 0.6 | L16: 0.5 | M16: 0.4 | N16: 0.4 | O16: 0.4
B18: Brazilian Credit portfolio breakdown | Abertura dos recebíveis de crédito do Brasil - US$ Billion*
B19: Current | À vista | C19: 3.7 | D19: 3.4 | E19: 3 | F19: 2.9 | G19: 2.8 | H19: 2.2 | I19: 2 | J19: 1.9 | K19: 1.4 | L19: 1.5 | M19: 1.1 | N19: 1 | O19: 1
B20: Installments without interest | Parcelados sem juros | C20: 3.5 | D20: 3.3 | E20: 2.8 | F20: 2.7 | G20: 2.7 | H20: 2.2 | I20: 1.8 | J20: 1.7 | K20: 1.3 | L20: 1.4 | M20: 1 | N20: 0.9 | O20: 0.9
B21: Installments with interest | Parcelados com juros | C21: 1.5 | D21: 1 | E21: 0.7 | F21: 0.5 | G21: 0.5 | H21: 0.3 | I21: 0.2 | J21: 0.2 | K21: 0.1 | L21: 0.1 | M21: 0.1 | N21: 0.1 | O21: 0.1
B22: Revolving | Rotativo | C22: 0.7 | D22: 0.6 | E22: 0.5 | F22: 0.4 | G22: 0.4 | H22: 0.3 | I22: 0.2 | J22: 0.2 | K22: 0.2 | L22: 0.2 | M22: 0.2 | N22: 0.2 | O22: 0.3
B23: Total | C23: 9.5 | D23: 8.4 | E23: 7 | F23: 6.5 | G23: 6.4 | H23: 5 | I23: 4.2 | J23: 4 | K23: 3 | L23: 3.2 | M23: 2.4 | N23: 2.2 | O23: 2.3
B25: *Includes information of Brazilian operation only
B26: *Inclui informações da operação brasileira apenas

Sheet Financing (Empréstimos)
B2: Nu Holdings Ltd. | G2: Nu Holdings Ltd.
B3: Financing | G3: Empréstimos
B4: Amounts in thousands of US$, unless otherwise noted | G4: Valores em US$ mil, exceto se mencionado de outra forma
B5: Back to Contents | G5: Retornar ao Índice
C10: 45016 | D10: 44926 | E10: 44834 | F10: 44742 | G10: 44651 | H10: 44561 | I10: 44469 | J10: 44377 | K10: 44286 | L10: 44196 | M10: 44104 | N10: 44012 | O10: 43921
C11: US$ | D11: US$ | E11: US$ | F11: US$ | G11: US$ | H11: US$ | I11: US$ | J11: US$ | K11: US$ | L11: US$ | M11: US$ | N11: US$ | O11: US$
B12: Borrowings and financing | Empréstimos | C12: 651181 | D12: 585568 | E12: 467959 | F12: 470881 | G12: 147645 | H12: 147243 | I12: 134398 | J12: 59165 | K12: 103220 | L12: 97454 | M12: 95719 | N12: 95202 | O12: 100597
B13: Sênior preferred shares | Ações preferenciais sênior | C13: 0 | D13: 0 | E13: 0 | F13: 0 | G13: 0 | H13: 0 | I13: 0 | J13: 0 | K13: 342450 | L13: 328394 | M13: 312942 | N13: 300000 | O13: 0
B14: Instruments eligible as capital | Instrumentos elegíveis a capital | C14: 2932 | D14: 11507 | E14: 19099 | F14: 18554 | G14: 20226 | H14: 12056 | I14: 12531 | J14: 14762 | K14: 13063 | L14: 15492 | M14: 15003 | N14: 15716 | O14: 15728
B15: Total raised funds | Total de captações | C15: 654113 | D15: 597075 | E15: 487058 | F15: 489435 | G15: 167871 | H15: 159299 | I15: 146929 | J15: 73927 | K15: 458733 | L15: 441340 | M15: 423664 | N15: 410918 | O15: 116325
